[
    {
        "title": "28030 / Greyhound Krakhops",
        "categories": "Hops Revolution, IPA, todo nuestro stock, Ultimas incorporaciones",
        "tipo": " Modern Ipa",
        "ABV": "5,7%",
        "Formato": " Lata 44cl",
        "Origen": " Madrid",
        "Descripción": " Ipa con lúpulos Mosaic Cryo, Azacca Cryo y Dorado T90.",
        "img": "https://www.labuenacerveza.com/wp-content/themes/mipro/assets/images/loading.gif"
    },
    {
        "title": "Abbaye des Rocs Brune",
        "categories": "Belga, Desde Belgium con Amor, todo nuestro stock",
        "tipo": " Belgian Dark Strong Ale ",
        "ABV": " 9%",
        "Formato": " Botella 33cl",
        "Origen": " Belgica",
        "Descripción": " Es una cerveza de pura malta (7 tipos), sin adición de",
        "img": "https://www.labuenacerveza.com/wp-content/themes/mipro/assets/images/loading.gif"
    },
    {
        "title": "Achel Blonde",
        "categories": "Belga, Desde Belgium con Amor, todo nuestro stock",
        "tipo": " Belgian Strong Ale",
        "ABV": " 8%",
        "Formato": " Botella 33cl",
        "Origen": " Bélgica",
        "Descripción": " Cerveza Trapense. Densa, dulce y amarga a lúpulo, con notas cítricas. Achel es una de",
        "img": "https://www.labuenacerveza.com/wp-content/themes/mipro/assets/images/loading.gif"
    },
    {
        "title": "Achel Bruin",
        "categories": "Belga, Desde Belgium con Amor, todo nuestro stock",
        "tipo": " Belgian Dark strong Ale",
        "ABV": " 8%",
        "Formato": " Botella 33cl",
        "Origen": " Bélgica",
        "Descripción": " Cerveza Trapense de un color caoba muy bello y una espuma beige bastante abundante. Es una",
        "img": "https://www.labuenacerveza.com/wp-content/themes/mipro/assets/images/loading.gif"
    },
    {
        "title": "Almogàver / Caravelle What’cha Want",
        "categories": "Hops Revolution, IPA, todo nuestro stock, Ultimas incorporaciones",
        "tipo": " New England Ipa",
        "ABV": " 6,8%",
        "Formato": " Botella 33cl",
        "Origen": " Cataluña",
        "Descripción": " Neipa dry hopped con Ahtanum, Hullmellon, El dorado y Idaho7.",
        "img": "https://www.labuenacerveza.com/wp-content/themes/mipro/assets/images/loading.gif"
    },
    {
        "title": "Anchor Steam Beer",
        "categories": "Klasikos Basikos, Lager, todo nuestro stock",
        "tipo": " Lager",
        "ABV": " 4,9%",
        "Formato": " Botella 35cl",
        "Origen": " Estados Unidos",
        "Descripción": " Color ámbar profundo. Aroma balanceado de grano tostado y lúpulo, ligeramente afrutado",
        "img": "https://www.labuenacerveza.com/wp-content/themes/mipro/assets/images/loading.gif"
    },
    {
        "title": "Arpus DDH Vic Secret x Galaxy DIPA",
        "categories": "Hops Revolution, IPA, todo nuestro stock, Ultimas incorporaciones",
        "tipo": " Doble New England Ipa ",
        "ABV": " 8%",
        "Formato": " Lata 44cl",
        "Origen": " Letonia",
        "Descripción": " Imperial Neipa con lúpulos Vic Secret y Galaxy.",
        "img": "https://www.labuenacerveza.com/wp-content/themes/mipro/assets/images/loading.gif"
    },
    {
        "title": "Augustiner Edelstoff",
        "categories": "Klasikos Basikos, Lager, todo nuestro stock",
        "tipo": " Lager Helles ",
        "ABV": " 5,6%",
        "Formato": " Botella 50cl",
        "Origen": " Alemania",
        "Descripción": " Cerveza color amarillo dorado, cristalina. Espuma blanca abundante, buena retención. Aromas a cereal,",
        "img": "https://www.labuenacerveza.com/wp-content/themes/mipro/assets/images/loading.gif"
    },
    {
        "title": "Augustiner Helles",
        "categories": "Klasikos Basikos, Lager, todo nuestro stock",
        "tipo": " Lager Hell",
        "ABV": " 5,2%",
        "Formato": " Botella 50cl",
        "Origen": " Alemania ",
        "Descripción": " Lagerbier Hell es una cerveza elaborada en Munich en Augustiner Bräu, una de",
        "img": "https://www.labuenacerveza.com/wp-content/themes/mipro/assets/images/loading.gif"
    },
    {
        "title": "Augustiner Weissbier",
        "categories": "Klasikos Basikos, todo nuestro stock, Trigo",
        "tipo": " Weizen, Weissbier (trigo alemán) ",
        "ABV": " 5,4%",
        "Formato": " Botella 50cl",
        "Origen": " Alemania",
        "Descripción": " Cerveza alemana de trigo de la fabrica más antigua de Munich.",
        "img": "https://www.labuenacerveza.com/wp-content/themes/mipro/assets/images/loading.gif"
    },
    {
        "title": "Ayinger Celebrator",
        "categories": "Klasikos Basikos, Lager, todo nuestro stock",
        "tipo": " Doppelbock ",
        "ABV": " 6,7%",
        "Formato": " Botella 33cl",
        "Origen": " Alemania ",
        "Descripción": " Doppelbock oscura de color negro rojizo y cuerpo generoso. En aroma predominan las maltas,",
        "img": "https://www.labuenacerveza.com/wp-content/themes/mipro/assets/images/loading.gif"
    },
    {
        "title": "Ayinger Kellerbier",
        "categories": "Klasikos Basikos, Lager, todo nuestro stock",
        "tipo": " Kellerbier ",
        "ABV": " 4,9%",
        "Formato": " Botella 50cl",
        "Origen": " Alemania",
        "Descripción": " Cerveza Lager de bodega sin filtrar, con ligera turbidez y agradable sabor amargo. Como",
        "img": "https://www.labuenacerveza.com/wp-content/themes/mipro/assets/images/loading.gif"
    },
    {
        "title": "Ayinger Lager Hell",
        "categories": "Klasikos Basikos, Lager, todo nuestro stock",
        "tipo": " Lager Helles",
        "ABV": " 4,9%",
        "Formato": " Botella 50cl",
        "Origen": " Alemania",
        "Descripción": " Lager Hell de Ayinger es un cerveza artesanal de estilo Dortmunder. Lager Hell",
        "img": "https://www.labuenacerveza.com/wp-content/themes/mipro/assets/images/loading.gif"
    },
    {
        "title": "Bacchus Frambozenbier",
        "categories": "Acid Power, Belga, Desde Belgium con Amor, todo nuestro stock",
        "tipo": " Oud Bruin / Red Flanders ",
        "ABV": " 5%",
        "Formato": " Botella 37,5cl",
        "Origen": " Bélgica",
        "Descripción": " Cerveza belga dulce, ácida y afrutada de estilo Flanders Red Ale elaborada con frambuesas.",
        "img": "https://www.labuenacerveza.com/wp-content/themes/mipro/assets/images/loading.gif"
    },
    {
        "title": "Baobeer B&W Colobus",
        "categories": "Petroleos, Porter, todo nuestro stock, Ultimas incorporaciones",
        "tipo": " Milk Chocolate Porter",
        "ABV": " 6,6%",
        "Formato": " Botella 33cl",
        "Origen": " País Vasco",
        "Descripción": " Porter con lactosa y cacao de Tanzania.",
        "img": "https://www.labuenacerveza.com/wp-content/themes/mipro/assets/images/loading.gif"
    },
    {
        "title": "Baobeer Cassava",
        "categories": "Hops Revolution, IPA, todo nuestro stock, Ultimas incorporaciones",
        "tipo": " New England Ipa",
        "ABV": " 6,5%",
        "Formato": " Lata 44cl",
        "Origen": " País Vasco",
        "Descripción": " Neipa DIP HOP + DDH. Cashmere, Idaho 7, Mosaic, Cryo Ekuanot.",
        "img": "https://www.labuenacerveza.com/wp-content/themes/mipro/assets/images/loading.gif"
    },
    {
        "title": "Baobeer Mona Monkey",
        "categories": "Petroleos, Porter, todo nuestro stock, Ultimas incorporaciones",
        "tipo": " American Porter ",
        "ABV": " 6,6%",
        "Formato": " Botella 33cl",
        "Origen": " País Vasco",
        "Descripción": " Porter lupulada con un generoso dry-hop del lúpulo experimental HBC472. Aromas a caramelo, cacao, café, madera",
        "img": "https://www.labuenacerveza.com/wp-content/themes/mipro/assets/images/loading.gif"
    },
    {
        "title": "Basqueland / Garage Fat Pocket",
        "categories": "Hops Revolution, IPA, todo nuestro stock, Ultimas incorporaciones",
        "tipo": " Doble Ipa",
        "ABV": " 8%",
        "Formato": " Lata 44cl",
        "Origen": " Pais Vasco",
        "Descripción": " Dipa colaboración con Garage con lúpulos Citra, Nelson Sauvin y Simcoe.",
        "img": "https://www.labuenacerveza.com/wp-content/themes/mipro/assets/images/loading.gif"
    },
    {
        "title": "Basqueland Bon Bon Bonanza",
        "categories": "Petroleos, Porter, todo nuestro stock, Ultimas incorporaciones",
        "tipo": " Imperial Porter",
        "ABV": " 11,5%",
        "Formato": " Lata 44cl",
        "Origen": " Pais Vasco ",
        "Descripción": " Imperial Porter con haba tonka.",
        "img": "https://www.labuenacerveza.com/wp-content/themes/mipro/assets/images/loading.gif"
    },
    {
        "title": "Basqueland Champoy",
        "categories": "Acid Power, Hops Revolution, IPA, Sour, todo nuestro stock, Ultimas incorporaciones",
        "tipo": " Fruit Gose ",
        "ABV": " 4,5%",
        "Formato": " Lata 44cl",
        "Origen": " Pais Vasco",
        "Descripción": " Fruit Sour Gose con sal, frambuesa y arándano.",
        "img": "https://www.labuenacerveza.com/wp-content/themes/mipro/assets/images/loading.gif"
    },
    {
        "title": "Basqueland Escondido",
        "categories": "Hops Revolution, IPA, todo nuestro stock, Ultimas incorporaciones",
        "tipo": " West Coast Ipa",
        "ABV": " 6, 3%",
        "Formato": " Lata 44cl",
        "Origen": " Pais Vasco",
        "Descripción": " West Coast Ipa single hop con lúpulo Simcoe.",
        "img": "https://www.labuenacerveza.com/wp-content/themes/mipro/assets/images/loading.gif"
    },
    {
        "title": "Basqueland Freebird",
        "categories": "Hops Revolution, IPA, Sin Gluten, todo nuestro stock, Ultimas incorporaciones",
        "tipo": " West Coast Ipa",
        "ABV": " 6%",
        "Formato": " Lata 33cl",
        "Origen": " Pais Vasco",
        "Descripción": " Ipa sin gluten de color dorado y casi cristalino, tiene aromas a resina de",
        "img": "https://www.labuenacerveza.com/wp-content/themes/mipro/assets/images/loading.gif"
    },
    {
        "title": "Basqueland High Visibility Vest",
        "categories": "Hops Revolution, IPA, todo nuestro stock, Ultimas incorporaciones",
        "tipo": " New England Ipa",
        "ABV": " 6%",
        "Formato": " Lata 44cl",
        "Origen": " Pais Vasco ",
        "Descripción": " Neipa con lúpulos Ella, Mosaic, Rakau.",
        "img": "https://www.labuenacerveza.com/wp-content/themes/mipro/assets/images/loading.gif"
    },
    {
        "title": "Basqueland Imparable",
        "categories": "Hops Revolution, IPA, todo nuestro stock, Ultimas incorporaciones",
        "tipo": " West Coast Ipa",
        "ABV": " 6, 8%",
        "Formato": " Botella/lata 33cl",
        "Origen": " Pais Vasco",
        "Descripción": " Es una IPA hecha al estilo de la costa oeste de los EEUU. De",
        "img": "https://www.labuenacerveza.com/wp-content/themes/mipro/assets/images/loading.gif"
    },
    {
        "title": "Basqueland Into the Abyss",
        "categories": "Petroleos, Stout, todo nuestro stock, Ultimas incorporaciones",
        "tipo": " Pastry Stout",
        "ABV": " 10%",
        "Formato": " Lata 44cl",
        "Origen": " Pais Vasco",
        "Descripción": " Pastry Stout acondicionada con lactosa, coco tostado, vainilla de Madagascar e infusionado con ramas de",
        "img": "https://www.labuenacerveza.com/wp-content/themes/mipro/assets/images/loading.gif"
    },
    {
        "title": "Basqueland Karaoke Chain Gang",
        "categories": "Hops Revolution, IPA, todo nuestro stock, Ultimas incorporaciones",
        "tipo": " New England Ipa",
        "ABV": " 6%",
        "Formato": " Lata 44cl",
        "Origen": " Pais Vasco",
        "Descripción": " New England Ipa con lúpulos Bru-I, Azacca, Ekuanot Cryo y Ekuanot.",
        "img": "https://www.labuenacerveza.com/wp-content/themes/mipro/assets/images/loading.gif"
    },
    {
        "title": "Basqueland Sweatpant Samurai",
        "categories": "Hops Revolution, IPA, todo nuestro stock, Ultimas incorporaciones",
        "tipo": " Oat Cream New England Ipa",
        "ABV": " 6,5%",
        "Formato": " Lata 44cl",
        "Origen": " Pais Vasco",
        "Descripción": " Oat Cream IPA cerveza turbia y densa gracias a la adicción",
        "img": "https://www.labuenacerveza.com/wp-content/themes/mipro/assets/images/loading.gif"
    },
    {
        "title": "Blanche de Namur",
        "categories": "Belga, Desde Belgium con Amor, Klasikos Basikos, todo nuestro stock, Trigo",
        "tipo": " Witbier (trigo Belga)",
        "ABV": " 4,5%",
        "Formato": " Botella 33cl",
        "Origen": " Belgica ",
        "Descripción": " Cerveza de trigo belga (estilo Witbier o Blanche) de 4.5%, ABV aromatizada",
        "img": "https://www.labuenacerveza.com/wp-content/themes/mipro/assets/images/loading.gif"
    },
    {
        "title": "Brasserie 28 Imperial Stout",
        "categories": "Petroleos, Stout, todo nuestro stock",
        "tipo": " Imperial Stout",
        "ABV": " 12%",
        "Formato": " Botella 33cl",
        "Origen": " Bélgica",
        "Descripción": " Ligera a pesar de su graduación alcohólica potente.Sabor a maltas tostadas, chocolate, café, frutas negras y",
        "img": "https://www.labuenacerveza.com/wp-content/themes/mipro/assets/images/loading.gif"
    },
    {
        "title": "Brew By Numbers 05|India Pale Ale – Costa Oeste (2022)",
        "categories": "Hops Revolution, IPA, todo nuestro stock, Ultimas incorporaciones",
        "tipo": " West Coast Ipa",
        "ABV": " 6, 2%",
        "Formato": " Lata 44cl",
        "Origen": " Inglaterra",
        "Descripción": " West Coast Ipa con aromas cítricos como naranja y pomelo con final a pino.",
        "img": "https://www.labuenacerveza.com/wp-content/themes/mipro/assets/images/loading.gif"
    },
    {
        "title": "Brew By Numbers 10|Coffee Porter – Mocha CBD",
        "categories": "Petroleos, Porter, todo nuestro stock, Ultimas incorporaciones",
        "tipo": " Coffee Porter",
        "ABV": " 6,5%",
        "Formato": " Lata 44cl",
        "Origen": " Inglaterra",
        "Descripción": " Esta colaboración entre Brew By Numbers, HASBEAN y Green Machine combina todo el sabor de un",
        "img": "https://www.labuenacerveza.com/wp-content/themes/mipro/assets/images/loading.gif"
    },
    {
        "title": "Breworkers BW03",
        "categories": "Hops Revolution, IPA, Red Ale, todo nuestro stock, Ultimas incorporaciones",
        "tipo": " Red Ipa",
        "ABV": " 6%",
        "Formato": " Lata 44cl",
        "Origen": " Madrid",
        "Descripción": " Red Ipa con lúpulos Chinook, Simcoe y Amarillo.",
        "img": "https://www.labuenacerveza.com/wp-content/themes/mipro/assets/images/loading.gif"
    },
    {
        "title": "Brugse Zot",
        "categories": "Belga, Desde Belgium con Amor, todo nuestro stock",
        "tipo": " Belgian Bolnd Ale",
        "ABV": " 6%",
        "Formato": " Botella 33cl",
        "Origen": " Bélgica",
        "Descripción": " Cerveza rubia con aromas afrutados y florales. Sabor dulce, con notas especiadas. Regusto seco y corto.",
        "img": "https://www.labuenacerveza.com/wp-content/themes/mipro/assets/images/loading.gif"
    },
    {
        "title": "Caleya Forest Vibes",
        "categories": "Acid Power, Sour, todo nuestro stock, Ultimas incorporaciones",
        "tipo": " Fruit Sour",
        "ABV": " 5,8%",
        "Formato": " Lata 44cl",
        "Origen": " Asturias",
        "Descripción": " Cerveza ácida con arándano, frambuesa, fresa y lactosa.",
        "img": "https://www.labuenacerveza.com/wp-content/themes/mipro/assets/images/loading.gif"
    },
    {
        "title": "Cantillon Rosé de Gambrinus 75cl",
        "categories": "Acid Power, Belga, Desde Belgium con Amor, Into the wild, Lambic, todo nuestro stock",
        "tipo": " Fruit Lambic",
        "ABV": " 5%",
        "Formato": " Botella 75cl",
        "Origen": " Bélgica",
        "Descripción": " Cerveza de fermentación espontánea (Lambic) sin filtrar ni pasteurizar elaborada con 200 gr. por litro de frambuesas",
        "img": "https://www.labuenacerveza.com/wp-content/themes/mipro/assets/images/loading.gif"
    },
    {
        "title": "Castelló Beer Factory Blackout",
        "categories": "Petroleos, Stout, todo nuestro stock, Ultimas incorporaciones",
        "tipo": " Imperial Milk Stout",
        "ABV": " 9,5%",
        "Formato": " Lata 33cl",
        "Origen": " Comunidad Valenciana",
        "Descripción": " Imperial Stout densa y cremosa, elaborada con naranja y chocolate.",
        "img": "https://www.labuenacerveza.com/wp-content/themes/mipro/assets/images/loading.gif"
    },
    {
        "title": "Castelló Beer Factory Freedom",
        "categories": "Hops Revolution, IPA, sin Alcohol, todo nuestro stock, Ultimas incorporaciones",
        "tipo": " Ipa Sin Alcohol",
        "ABV": " 1%",
        "Formato": " Botella 33cl",
        "Origen": " Comunidad Valenciana",
        "Descripción": " Ipa sin alcohol elaborada con Doble Dry Hopping de lúpulos Simcoe, Citra",
        "img": "https://www.labuenacerveza.com/wp-content/themes/mipro/assets/images/loading.gif"
    },
    {
        "title": "Charles Quint Blond",
        "categories": "Belga, Desde Belgium con Amor, todo nuestro stock",
        "tipo": " Belgian Strong Ale",
        "ABV": " 8,5%",
        "Formato": " Botella 33cl",
        "Origen": " Bélgica",
        "Descripción": " Es una cerveza rubia muy clarita, aromática con notas a especias, caramelo, bastante maltosa",
        "img": "https://www.labuenacerveza.com/wp-content/themes/mipro/assets/images/loading.gif"
    },
    {
        "title": "Charles Quint Rubí Red",
        "categories": "Belga, Desde Belgium con Amor, todo nuestro stock",
        "tipo": " Belgian Dark Strong Ale",
        "ABV": " 8,5%",
        "Formato": " Botella 33cl",
        "Origen": " Bélgica",
        "Descripción": " Color ojo rubí, ligeramente dulce, aroma de lúpulo. Cerveza con espuma cremosa",
        "img": "https://www.labuenacerveza.com/wp-content/themes/mipro/assets/images/loading.gif"
    },
    {
        "title": "Cierzo Vértigo",
        "categories": "Hops Revolution, IPA, todo nuestro stock, Ultimas incorporaciones",
        "tipo": " New England Doble Ipa",
        "ABV": " 9%",
        "Formato": " Lata 44cl",
        "Origen": " Zaragoza",
        "Descripción": " Hazy DIPA con aromas cítricos y afrutados.",
        "img": "https://www.labuenacerveza.com/wp-content/themes/mipro/assets/images/loading.gif"
    },
    {
        "title": "Cigar City Fancy Papers",
        "categories": "Hops Revolution, IPA, todo nuestro stock, Ultimas incorporaciones",
        "tipo": " New England Ipa",
        "ABV": " 6,5%",
        "Formato": " Lata 35cl",
        "Origen": " Estados Unidos",
        "Descripción": " Ipa con aromas cítricos, herbales y tropicales.",
        "img": "https://www.labuenacerveza.com/wp-content/themes/mipro/assets/images/loading.gif"
    },
    {
        "title": "Cigar City Florida Man",
        "categories": "Hops Revolution, IPA, todo nuestro stock, Ultimas incorporaciones",
        "tipo": " Doble Ipa",
        "ABV": " 8,5%",
        "Formato": " Lata 35cl",
        "Origen": " Estados Unidos",
        "Descripción": " DIpa",
        "img": "https://www.labuenacerveza.com/wp-content/themes/mipro/assets/images/loading.gif"
    },
    {
        "title": "Cigar City Jai Alai",
        "categories": "Hops Revolution, IPA, todo nuestro stock, Ultimas incorporaciones",
        "tipo": " Ipa",
        "ABV": " 7,5%",
        "Formato": " Lata 35cl",
        "Origen": " Estados Unidos",
        "Descripción": " Ipa con aromas cítricos, herbales y resinosos.",
        "img": "https://www.labuenacerveza.com/wp-content/themes/mipro/assets/images/loading.gif"
    },
    {
        "title": "Cigar City Maduro Brown Ale",
        "categories": "brown Ale, Caramelazos, todo nuestro stock, Ultimas incorporaciones",
        "tipo": " Brown Ale",
        "ABV": " 5,5%",
        "Formato": " Lata 35cl",
        "Origen": " Estados Unidos",
        "Descripción": " Brown ale con aromas a caramelo, chocolate y algo de café con final",
        "img": "https://www.labuenacerveza.com/wp-content/themes/mipro/assets/images/loading.gif"
    },
    {
        "title": "Cigar City Margarita Gose",
        "categories": "Acid Power, Sour, todo nuestro stock, Ultimas incorporaciones",
        "tipo": " Fruit Gose",
        "ABV": " 4,2%",
        "Formato": " Lata 35cl",
        "Origen": " Estados Unidos",
        "Descripción": " Cerveza ácida con naranja, lima y sal.",
        "img": "https://www.labuenacerveza.com/wp-content/themes/mipro/assets/images/loading.gif"
    },
    {
        "title": "Cosa Nostra Lupara",
        "categories": "Hops Revolution, IPA, todo nuestro stock, Ultimas incorporaciones",
        "tipo": " Ddh American Ipa",
        "ABV": " 7,5%",
        "Formato": " Lata 44cl",
        "Origen": " Valencia",
        "Descripción": " American Ipa con lúpulos HBC586, Ekuanot y Galaxy.",
        "img": "https://www.labuenacerveza.com/wp-content/themes/mipro/assets/images/loading.gif"
    },
    {
        "title": "De Cam Kriek Lambiek 75cl",
        "categories": "Acid Power, Belga, Desde Belgium con Amor, Into the wild, Lambic, todo nuestro stock",
        "tipo": " Fruit Lambic",
        "ABV": " 6,5%",
        "Formato": " Botella 75cl",
        "Origen": " Bélgica",
        "Descripción": " Lambic madurada durante dos años con cerezas, 40 kg por cada 100 litros.",
        "img": "https://www.labuenacerveza.com/wp-content/themes/mipro/assets/images/loading.gif"
    },
    {
        "title": "De Cam Oude Lambiek 37cl",
        "categories": "Acid Power, Belga, Desde Belgium con Amor, Into the wild, Lambic, todo nuestro stock",
        "tipo": " Lambic",
        "ABV": " 6,5%",
        "Formato": " Botella 37,5cl",
        "Origen": " Bélgica",
        "Descripción": " Cerveza lambica madurada durante 3 años en barriles de madera.",
        "img": "https://www.labuenacerveza.com/wp-content/themes/mipro/assets/images/loading.gif"
    },
    {
        "title": "De Moersleutel Double Roast Planadas",
        "categories": "Petroleos, Stout, todo nuestro stock",
        "tipo": " Imperial Stout",
        "ABV": " 10%",
        "Formato": " Lata 44cl",
        "Origen": " Holanda",
        "Descripción": " Imperial Stout elaborada con café Colombiano de la zona de planadas.",
        "img": "https://www.labuenacerveza.com/wp-content/themes/mipro/assets/images/loading.gif"
    },
    {
        "title": "Delirium Nocturnum",
        "categories": "Belga, Desde Belgium con Amor, todo nuestro stock",
        "tipo": " Belgian Dark Strong Ale",
        "ABV": " 9%",
        "Formato": " Botella 33cl",
        "Origen": " Bélgica",
        "Descripción": " Color marrón oscuro rojizo. Aromas a caramelo, moka y chocolate, especias. Sabor dulce",
        "img": "https://www.labuenacerveza.com/wp-content/themes/mipro/assets/images/loading.gif"
    },
    {
        "title": "Delirium Tremens",
        "categories": "Belga, Desde Belgium con Amor, todo nuestro stock",
        "tipo": " Belgian Strong Golden Ale",
        "ABV": " 8,5%",
        "Formato": " Botella 33cl",
        "Origen": " Bélgica",
        "Descripción": " Cerveza rubia fuerte, aromas especiados, dulce, afrutados y herbácea. Sabor dulce y final",
        "img": "https://www.labuenacerveza.com/wp-content/themes/mipro/assets/images/loading.gif"
    },
    {
        "title": "Dougall’s 942",
        "categories": "Hops Revolution, Pale Ale, Sin Gluten, todo nuestro stock",
        "tipo": " Pale Ale",
        "ABV": " 4,2%",
        "Formato": " Botella 33cl",
        "Origen": " Cantabria",
        "Descripción": " Pale Ale sin gluten. De color rubio dorado y ligeramente turbia es una cerveza aromática con apuntes cítricos,",
        "img": "https://www.labuenacerveza.com/wp-content/themes/mipro/assets/images/loading.gif"
    },
    {
        "title": "Dougall’s Doble IPA",
        "categories": "Hops Revolution, IPA, todo nuestro stock, Ultimas incorporaciones",
        "tipo": " Doble Ipa",
        "ABV": " 8,5%",
        "Formato": " Botella 33cl",
        "Origen": " Cantabria",
        "Descripción": " Dipa con lúpulos Simcoe, Mosaic, Citra, Amarillo y Loral.",
        "img": "https://www.labuenacerveza.com/wp-content/themes/mipro/assets/images/loading.gif"
    },
    {
        "title": "Dougall’s IPA 4",
        "categories": "Hops Revolution, IPA, Sin Gluten, todo nuestro stock",
        "tipo": " Ipa",
        "ABV": " 6%",
        "Formato": " Botella 33cl",
        "Origen": " Cantabria",
        "Descripción": " Ipa sin gluten, con lupulos Mosaic y Centennial. De color dorado pajizo. Aromas y sabores cítricos como el pomelo",
        "img": "https://www.labuenacerveza.com/wp-content/themes/mipro/assets/images/loading.gif"
    },
    {
        "title": "Drunken Bros Black & Deep",
        "categories": "Petroleos, Stout, todo nuestro stock, Ultimas incorporaciones",
        "tipo": " Imperial Stout Barrel Aged",
        "ABV": " 10%",
        "Formato": " Lata 33cl",
        "Origen": " Pais Vasco",
        "Descripción": " Imperial Stout envejecida en barrica. Aromas a café, chocolate y licor.",
        "img": "https://www.labuenacerveza.com/wp-content/themes/mipro/assets/images/loading.gif"
    },
    {
        "title": "Drunken Bros Kill Mister (Nightmare Series)",
        "categories": "Barley Wine, Caramelazos, todo nuestro stock, Ultimas incorporaciones",
        "tipo": " Barley Wine",
        "ABV": " 12,5%",
        "Formato": " Lata 33cl",
        "Origen": " Pais Vasco",
        "Descripción": " Barley Wine madurada en barricas de Whisky. Aromas a frutas pasas y dátiles. En boca",
        "img": "https://www.labuenacerveza.com/wp-content/themes/mipro/assets/images/loading.gif"
    },
    {
        "title": "Drunken Bros Loki (Nightmare Series)",
        "categories": "Petroleos, Stout, todo nuestro stock, Ultimas incorporaciones",
        "tipo": " Imperial Milk Stout",
        "ABV": " 9,2%",
        "Formato": " Lata 33cl",
        "Origen": " Pais Vasco",
        "Descripción": " Imperial Milk Stout elaborada con café.",
        "img": "https://www.labuenacerveza.com/wp-content/themes/mipro/assets/images/loading.gif"
    },
    {
        "title": "Drunken Bros Shannon",
        "categories": "Hops Revolution, IPA, todo nuestro stock, Ultimas incorporaciones",
        "tipo": " West Coast Ipa",
        "ABV": " 6,8%",
        "Formato": " Lata 44cl",
        "Origen": " Pais Vasco",
        "Descripción": " West Coast Ipa con lúpulos Chinook, Ekuanot y Amarillo.",
        "img": "https://www.labuenacerveza.com/wp-content/themes/mipro/assets/images/loading.gif"
    },
    {
        "title": "Dry & Bitter Dwell In the Fog",
        "categories": "Hops Revolution, IPA, todo nuestro stock, Ultimas incorporaciones",
        "tipo": " New England Ipa",
        "ABV": " 6%",
        "Formato": " Lata 44cl",
        "Origen": " Dinamarca",
        "Descripción": " Neipa DDH con lúpulos Talus y El Dorado.",
        "img": "https://www.labuenacerveza.com/wp-content/themes/mipro/assets/images/loading.gif"
    },
    {
        "title": "Dry & Bitter Hydroglyph",
        "categories": "Hops Revolution, IPA, todo nuestro stock, Ultimas incorporaciones",
        "tipo": " Rye Ipa",
        "ABV": " 7%",
        "Formato": " Lata 44cl",
        "Origen": " Dinamarca",
        "Descripción": " Ipa con malta de centeno y lúpulos Idaho 7, Citra y Ekuanot.",
        "img": "https://www.labuenacerveza.com/wp-content/themes/mipro/assets/images/loading.gif"
    },
    {
        "title": "Dry & Bitter Romanoid",
        "categories": "Hops Revolution, IPA, todo nuestro stock, Ultimas incorporaciones",
        "tipo": " Doble New England Ipa",
        "ABV": " 7,5%",
        "Formato": " Lata 44cl",
        "Origen": " Dinamarca",
        "Descripción": " Doble Neipa DDH con lúpulos Strata, Citra y Ekuanot.",
        "img": "https://www.labuenacerveza.com/wp-content/themes/mipro/assets/images/loading.gif"
    },
    {
        "title": "Dry & Bitter UW",
        "categories": "Hops Revolution, IPA, todo nuestro stock, Ultimas incorporaciones",
        "tipo": " Hazy Ipa",
        "ABV": " 6%",
        "Formato": " Lata 44cl",
        "Origen": " Dinamarca",
        "Descripción": " Hazy American Ipa tropical y resinosa.",
        "img": "https://www.labuenacerveza.com/wp-content/themes/mipro/assets/images/loading.gif"
    },
    {
        "title": "Duchesse de Bourgogne",
        "categories": "Acid Power, Belga, Desde Belgium con Amor, todo nuestro stock",
        "tipo": " Oud Bruin / Red Flanders",
        "ABV": " 6,2%",
        "Formato": " Botella 25cl",
        "Origen": " Bélgica",
        "Descripción": " Cerveza belga de estilo Ale Roja de 6.2% ABV de marcado carácter agrio",
        "img": "https://www.labuenacerveza.com/wp-content/themes/mipro/assets/images/loading.gif"
    },
    {
        "title": "Espiga Berliner Weisse",
        "categories": "Acid Power, Berliner Weisse, Sour, todo nuestro stock, Ultimas incorporaciones",
        "tipo": " Fruit Berliner Weisse",
        "ABV": " 3,5%",
        "Formato": " Botella 33cl",
        "Origen": " Cataluña",
        "Descripción": " Cerveza ácida elaborada con melocotón.",
        "img": "https://www.labuenacerveza.com/wp-content/themes/mipro/assets/images/loading.gif"
    },
    {
        "title": "Espiga Blonde Ale (sin gluten)",
        "categories": "Hops Revolution, Pale Ale, todo nuestro stock, Ultimas incorporaciones",
        "tipo": " American Pale Ale",
        "ABV": " 4,5%",
        "Formato": " Botella 33cl",
        "Origen": " Cataluña",
        "Descripción": " Apa sin gluten con lúpulos Mosaic, Cascade & Citra. Toques cítricos y tropicales.",
        "img": "https://www.labuenacerveza.com/wp-content/themes/mipro/assets/images/loading.gif"
    },
    {
        "title": "Espiga Midnight Dream",
        "categories": "Hops Revolution, IPA, todo nuestro stock, Ultimas incorporaciones",
        "tipo": " New England Ipa",
        "ABV": " 6,3%",
        "Formato": " Lata 44cl",
        "Origen": " Cataluña",
        "Descripción": " DDH Ipa  con lúpulos Nelson sauvin y Citra.",
        "img": "https://www.labuenacerveza.com/wp-content/themes/mipro/assets/images/loading.gif"
    },
    {
        "title": "Espiga Rainbow Keeper",
        "categories": "Hops Revolution, IPA, todo nuestro stock, Ultimas incorporaciones",
        "tipo": " Session Ipa",
        "ABV": " 4,5%",
        "Formato": " Lata 44cl",
        "Origen": " Cataluña",
        "Descripción": "  Session Ipa con lúpulos  Amarillo, Simcoe, Citra y Mosaic.",
        "img": "https://www.labuenacerveza.com/wp-content/themes/mipro/assets/images/loading.gif"
    },
    {
        "title": "Fauve Les Cerisiers De Mai",
        "categories": "Acid Power, Berliner Weisse, Sour, todo nuestro stock, Ultimas incorporaciones",
        "tipo": " Pastry Sour",
        "ABV": " 6,5%",
        "Formato": " Lata 33cl",
        "Origen": " Francia",
        "Descripción": " Pastry Sour elaborada con lactosa, cerezas, vainilla y haba tonka.",
        "img": "https://www.labuenacerveza.com/wp-content/themes/mipro/assets/images/loading.gif"
    },
    {
        "title": "Fauve Luxe, Calme Et Volupté",
        "categories": "Acid Power, Berliner Weisse, Sour, todo nuestro stock, Ultimas incorporaciones",
        "tipo": " Pastry Sour",
        "ABV": " 6,5%",
        "Formato": " Lata 33cl",
        "Origen": " Francia",
        "Descripción": " Pastry Gose elaborada con albaricoque, ruibarbo y haba tonka.",
        "img": "https://www.labuenacerveza.com/wp-content/themes/mipro/assets/images/loading.gif"
    },
    {
        "title": "Fauve Tout Le Reste N’est Rien",
        "categories": "Hops Revolution, IPA, todo nuestro stock, Ultimas incorporaciones",
        "tipo": " New England Ipa",
        "ABV": " 6,8%",
        "Formato": " Lata 33cl",
        "Origen": " Francia",
        "Descripción": " Neipa con doble dry hopping de lúpulos Galaxy y Lotus.",
        "img": "https://www.labuenacerveza.com/wp-content/themes/mipro/assets/images/loading.gif"
    },
    {
        "title": "Fermenterarna Four Years Celebration DIPA",
        "categories": "Hops Revolution, IPA, todo nuestro stock, Ultimas incorporaciones",
        "tipo": " New England Doble Ipa",
        "ABV": " 8%",
        "Formato": " Lata 44cl",
        "Origen": " Suecia",
        "Descripción": " Doble Neipa Ddh con lúpulos Galaxy y Citra cryo.",
        "img": "https://www.labuenacerveza.com/wp-content/themes/mipro/assets/images/loading.gif"
    },
    {
        "title": "Fermenterarna Four Years Celebration SOUR",
        "categories": "Acid Power, Sour, todo nuestro stock, Ultimas incorporaciones",
        "tipo": " Pastry Sour",
        "ABV": " 6%",
        "Formato": " Lata 44cl",
        "Origen": " Suecia",
        "Descripción": " Fruit Sour",
        "img": "https://www.labuenacerveza.com/wp-content/themes/mipro/assets/images/loading.gif"
    },
    {
        "title": "FlyBrew Blend 01",
        "categories": "Acid Power, Saison, Sour, todo nuestro stock, Ultimas incorporaciones",
        "tipo": " Wild Saison",
        "ABV": " 8%",
        "Formato": " Botella 37,5cl",
        "Origen": " Cataluña",
        "Descripción": " Blend entre barricas de una cerveza Brett Saison y una Wild Saison. Envejecida en barricas de",
        "img": "https://www.labuenacerveza.com/wp-content/themes/mipro/assets/images/loading.gif"
    },
    {
        "title": "FlyBrew Stratasphere",
        "categories": "Hops Revolution, IPA, todo nuestro stock, Ultimas incorporaciones",
        "tipo": " New England Ipa",
        "ABV": " 6%",
        "Formato": " Lata 44cl",
        "Origen": " Barcelona",
        "Descripción": " Neipa con lúpulos Strata, Citra y HBC472.",
        "img": "https://www.labuenacerveza.com/wp-content/themes/mipro/assets/images/loading.gif"
    },
    {
        "title": "FrauGruber cloak of Feathers",
        "categories": "Hops Revolution, IPA, todo nuestro stock, Ultimas incorporaciones",
        "tipo": " Hazy Doble Ipa",
        "ABV": " 8,6%",
        "Formato": " Lata 44cl",
        "Origen": " Alemania",
        "Descripción": " Dipa turbia con lúpulos Mosaic Spectrum, Galaxy, Simcoe, Rakau y Citra BBC.",
        "img": "https://www.labuenacerveza.com/wp-content/themes/mipro/assets/images/loading.gif"
    },
    {
        "title": "FrauGruber Purple Haze",
        "categories": "Hops Revolution, IPA, todo nuestro stock, Ultimas incorporaciones",
        "tipo": " American Ddh Ipa",
        "ABV": " 6,8%",
        "Formato": " Lata 44cl",
        "Origen": " Alemania",
        "Descripción": " Neipa elaborada con doble dry hopping de lúpulos  Mosaic T90, Mosaic Incognito y Mosaic BBC.",
        "img": "https://www.labuenacerveza.com/wp-content/themes/mipro/assets/images/loading.gif"
    },
    {
        "title": "Freddo Fox Under My Umbrella",
        "categories": "Acid Power, Berliner Weisse, Sour, todo nuestro stock, Ultimas incorporaciones",
        "tipo": " Fruit Berliner Weisse",
        "ABV": " 4,7%",
        "Formato": " Lata 33cl",
        "Origen": " Cataluña",
        "Descripción": " Cerveza ácida con fresas, vainilla de Madagascar y melocotón.",
        "img": "https://www.labuenacerveza.com/wp-content/themes/mipro/assets/images/loading.gif"
    },
    {
        "title": "Freddo Fox Urban Jungle",
        "categories": "Acid Power, Sour, todo nuestro stock, Ultimas incorporaciones",
        "tipo": " Fruit Gose",
        "ABV": " 6%",
        "Formato": " Lata 33cl",
        "Origen": " Cataluña",
        "Descripción": " Cerveza ácida con Frambuesa, Mora, fruta de la pasión, melocotón, vainilla y sal.",
        "img": "https://www.labuenacerveza.com/wp-content/themes/mipro/assets/images/loading.gif"
    },
    {
        "title": "Fuerst Wiacek Computer Rage",
        "categories": "Hops Revolution, IPA, todo nuestro stock, Ultimas incorporaciones",
        "tipo": " Hazy Session Ipa",
        "ABV": " 4,8%",
        "Formato": " Lata 44cl",
        "Origen": " Alemania",
        "Descripción": " Session Ipa Dry hopped con Citra, Idaho 7 y Motueka.",
        "img": "https://www.labuenacerveza.com/wp-content/themes/mipro/assets/images/loading.gif"
    },
    {
        "title": "Fuerst Wiacek Dream #10",
        "categories": "Hops Revolution, IPA, todo nuestro stock, Ultimas incorporaciones",
        "tipo": " New England Ipa",
        "ABV": " 6,8%",
        "Formato": " Lata 44cl",
        "Origen": " Alemania",
        "Descripción": " Neipa dry-hopped with Citra y Mosaic. Tanto la Dream #9 como la Dream",
        "img": "https://www.labuenacerveza.com/wp-content/themes/mipro/assets/images/loading.gif"
    },
    {
        "title": "Fuerst Wiacek Dream #9",
        "categories": "Hops Revolution, IPA, todo nuestro stock, Ultimas incorporaciones",
        "tipo": " New England Ipa",
        "ABV": " 6,8%",
        "Formato": " Lata 44cl",
        "Origen": " Alemania",
        "Descripción": " Neipa dry-hopped with Citra y Mosaic. Tanto la Dream #9 como la Dream",
        "img": "https://www.labuenacerveza.com/wp-content/themes/mipro/assets/images/loading.gif"
    },
    {
        "title": "Galway Bay Goodbye Blue Monday",
        "categories": "Hops Revolution, IPA, todo nuestro stock, Ultimas incorporaciones",
        "tipo": " Oatmeal Ipa",
        "ABV": " 6,6%",
        "Formato": " Lata 44cl",
        "Origen": " Irlanda",
        "Descripción": " Ipa con mucha avena con lúpulos Columbus, Citra, Cascade y Mosaic.",
        "img": "https://www.labuenacerveza.com/wp-content/themes/mipro/assets/images/loading.gif"
    },
    {
        "title": "Galway Bay Little Feelings  Citra, Simcoe, Amarillo Pale Ale",
        "categories": "Hops Revolution, Pale Ale, todo nuestro stock, Ultimas incorporaciones",
        "tipo": " New England Pale Ale",
        "ABV": " 5%",
        "Formato": " Lata 44cl",
        "Origen": " Irlanda",
        "Descripción": " Neapa con lúpulos Citra, Simcoe y Amarillo.",
        "img": "https://www.labuenacerveza.com/wp-content/themes/mipro/assets/images/loading.gif"
    },
    {
        "title": "Gamma CryoPop Whirlyboy",
        "categories": "Hops Revolution, IPA, todo nuestro stock",
        "tipo": " New England Ipa",
        "ABV": " 7,5%",
        "Formato": " Lata 44cl",
        "Origen": " Dinamarca",
        "Descripción": " Neipa con lúpulos CryoPop, Loral y Simcoe.",
        "img": "https://www.labuenacerveza.com/wp-content/themes/mipro/assets/images/loading.gif"
    },
    {
        "title": "Gamma Freak Wave",
        "categories": "Hops Revolution, IPA, todo nuestro stock, Ultimas incorporaciones",
        "tipo": " New England Ipa",
        "ABV": " 6,5%",
        "Formato": " Lata 44cl",
        "Origen": " Dinamarca",
        "Descripción": " Neipa con lúpulos Cashmere, Mosaic y Citra.",
        "img": "https://www.labuenacerveza.com/wp-content/themes/mipro/assets/images/loading.gif"
    },
    {
        "title": "Garage / Oddity Time On Calm",
        "categories": "brown Ale, Caramelazos, Stout, todo nuestro stock, Ultimas incorporaciones",
        "tipo": " Brown Ale",
        "ABV": " 8%",
        "Formato": " Lata 44cl",
        "Origen": " Barcelona",
        "Descripción": " Brown Ale colaboración con Oddity.",
        "img": "https://www.labuenacerveza.com/wp-content/themes/mipro/assets/images/loading.gif"
    },
    {
        "title": "Garage Dream Alchemy",
        "categories": "Hops Revolution, IPA, todo nuestro stock, Ultimas incorporaciones",
        "tipo": " New England Ipa",
        "ABV": " 7%",
        "Formato": " Lata 44cl",
        "Origen": " Barcelona",
        "Descripción": " Neipa con lúpulos Enigma, Strata y Galaxy.",
        "img": "https://www.labuenacerveza.com/wp-content/themes/mipro/assets/images/loading.gif"
    },
    {
        "title": "Garage Heads",
        "categories": "Hops Revolution, IPA, todo nuestro stock, Ultimas incorporaciones",
        "tipo": " New England Ipa",
        "ABV": " 6%",
        "Formato": " Lata 44cl",
        "Origen": " Barcelona",
        "Descripción": " Neipa con lúpulos Simcoe, Strata y Mosaic.",
        "img": "https://www.labuenacerveza.com/wp-content/themes/mipro/assets/images/loading.gif"
    },
    {
        "title": "Garage Shallow Tek",
        "categories": "Hops Revolution, IPA, todo nuestro stock, Ultimas incorporaciones",
        "tipo": " Doble Ipa",
        "ABV": " 8%",
        "Formato": " Lata 44cl",
        "Origen": " Barcelona",
        "Descripción": " Doble IPA con lúpulos Azacca, Galaxy, Mosaic, Ekuanot Cryo y Sabro.",
        "img": "https://www.labuenacerveza.com/wp-content/themes/mipro/assets/images/loading.gif"
    },
    {
        "title": "Garage Tails",
        "categories": "Hops Revolution, IPA, todo nuestro stock, Ultimas incorporaciones",
        "tipo": " West Coast Ipa",
        "ABV": " 6%",
        "Formato": " Lata 44cl",
        "Origen": " Barcelona",
        "Descripción": " West Coast Ipa con lúpulos Simcoe, Strata y Mosaic.",
        "img": "https://www.labuenacerveza.com/wp-content/themes/mipro/assets/images/loading.gif"
    },
    {
        "title": "Garage Three Plus Four",
        "categories": "Hops Revolution, IPA, todo nuestro stock, Ultimas incorporaciones",
        "tipo": " New England Ipa",
        "ABV": " 7%",
        "Formato": " Lata 44cl",
        "Origen": " Barcelona",
        "Descripción": " Para celebrar nuestro séptimo cumpleaños decidimos elaborar un par de IPAs de 7 grados. THREE",
        "img": "https://www.labuenacerveza.com/wp-content/themes/mipro/assets/images/loading.gif"
    },
    {
        "title": "Garage Two Plus Five",
        "categories": "Hops Revolution, IPA, todo nuestro stock, Ultimas incorporaciones",
        "tipo": " New England Ipa",
        "ABV": " 7%",
        "Formato": " Lata 44cl",
        "Origen": " Barcelona",
        "Descripción": " Para celebrar nuestro séptimo cumpleaños decidimos elaborar un par de IPAs de 7 grados. TWO",
        "img": "https://www.labuenacerveza.com/wp-content/themes/mipro/assets/images/loading.gif"
    },
    {
        "title": "Garage Unnecessary Spaces",
        "categories": "Hops Revolution, IPA, todo nuestro stock, Ultimas incorporaciones",
        "tipo": " Doble Ipa",
        "ABV": " 8%",
        "Formato": " Lata 44cl",
        "Origen": " Barcelona",
        "Descripción": " Doble IPA con lúpulos Citra, Azacca, Azacca cryo y Saphir.",
        "img": "https://www.labuenacerveza.com/wp-content/themes/mipro/assets/images/loading.gif"
    },
    {
        "title": "Girardin Gueuze 1882",
        "categories": "Acid Power, Belga, Desde Belgium con Amor, Into the wild, Lambic, todo nuestro stock",
        "tipo": " Lambic Gueuze",
        "ABV": " 5%",
        "Formato": " Botella 75cl",
        "Origen": " Bélgica",
        "Descripción": " Cerveza Lambic Gueuze de color ambar y sabores ácidos que recuerdan al Chapán. Estilo muy recomendable para",
        "img": "https://www.labuenacerveza.com/wp-content/themes/mipro/assets/images/loading.gif"
    },
    {
        "title": "Gross Lonely Fans",
        "categories": "Hops Revolution, IPA, todo nuestro stock, Ultimas incorporaciones",
        "tipo": " New England Ipa",
        "ABV": " 7%",
        "Formato": " Lata 44cl",
        "Origen": " Pais Vasco",
        "Descripción": " Hazy Ipa",
        "img": "https://www.labuenacerveza.com/wp-content/themes/mipro/assets/images/loading.gif"
    },
    {
        "title": "Gross Topatik",
        "categories": "Hops Revolution, IPA, todo nuestro stock, Ultimas incorporaciones",
        "tipo": " New England Ipa",
        "ABV": " 6,5%",
        "Formato": " Lata 44cl",
        "Origen": " Pais Vasco",
        "Descripción": " Hazy Ipa con lúpulos Cryo Mosaic y Galaxy.",
        "img": "https://www.labuenacerveza.com/wp-content/themes/mipro/assets/images/loading.gif"
    },
    {
        "title": "Gulden Draak 9000 Quadruple",
        "categories": "Belga, Desde Belgium con Amor, todo nuestro stock",
        "tipo": " Belgian Dark Strong Ale",
        "ABV": " 10,5%",
        "Formato": " Botella 33cl",
        "Origen": " Bélgica",
        "Descripción": " Color dorado profundo entre ambarino y rubio",
        "img": "https://www.labuenacerveza.com/wp-content/themes/mipro/assets/images/loading.gif"
    },
    {
        "title": "Gulden Draak classic",
        "categories": "Belga, Desde Belgium con Amor, todo nuestro stock",
        "tipo": " Belgian Dark Strong Ale",
        "ABV": " 10,5%",
        "Formato": " Botella 33cl",
        "Origen": " Bélgica",
        "Descripción": " Cerveza belga fuerte en la que se ha utilizado levadura de vino",
        "img": "https://www.labuenacerveza.com/wp-content/themes/mipro/assets/images/loading.gif"
    },
    {
        "title": "Hanssens Cassis",
        "categories": "Acid Power, Belga, Desde Belgium con Amor, Into the wild, Lambic, todo nuestro stock",
        "tipo": " Fruit Lambic",
        "ABV": " 6%",
        "Formato": " Botella 37,5cl",
        "Origen": " Bélgica",
        "Descripción": " Cerveza de fermentación espontánea. Lambic con Grosellas negras.",
        "img": "https://www.labuenacerveza.com/wp-content/themes/mipro/assets/images/loading.gif"
    },
    {
        "title": "Hanssens Oude Gueuze 37,5cl",
        "categories": "Acid Power, Belga, Desde Belgium con Amor, Into the wild, Lambic, todo nuestro stock",
        "tipo": " Lambic Gueuze",
        "ABV": " 6%",
        "Formato": " Botella 37,5cl",
        "Origen": " Bélgica",
        "Descripción": " Como con todos las Gueuzes, Hanssens es una mezcla de varias cosechas para producir una lambic",
        "img": "https://www.labuenacerveza.com/wp-content/themes/mipro/assets/images/loading.gif"
    },
    {
        "title": "Hoegaarden Blanche",
        "categories": "Belga, Desde Belgium con Amor, Klasikos Basikos, todo nuestro stock, Trigo",
        "tipo": " Witbier (trigo Belga)",
        "ABV": " 4,9%",
        "Formato": " Botella 33cl",
        "Origen": " Belgica",
        "Descripción": " clásica cerveza de trigo belga, suave, ligera y agradable.",
        "img": "https://www.labuenacerveza.com/wp-content/themes/mipro/assets/images/loading.gif"
    },
    {
        "title": "Juguetes Perdidos El Matador",
        "categories": "Petroleos, Stout, todo nuestro stock, Ultimas incorporaciones",
        "tipo": " Imperial Stout",
        "ABV": " 10,5%",
        "Formato": " Lata 33cl",
        "Origen": " Argentina (fabricada en España)",
        "Descripción": " Imperial Stout con sabor a Imperial Stout. Británica y clásica.",
        "img": "https://www.labuenacerveza.com/wp-content/themes/mipro/assets/images/loading.gif"
    },
    {
        "title": "Kasteel Barista Chocolate Quad",
        "categories": "Belga, Desde Belgium con Amor, todo nuestro stock",
        "tipo": " Quadrupel Belgian Dark Strong Ale",
        "ABV": " 11%",
        "Formato": " Botella 33cl",
        "Origen": " Bélgica",
        "Descripción": " Barista Chocolate Quad ofrece notas claras de caramelo, toffee y chocolate.",
        "img": "https://www.labuenacerveza.com/wp-content/themes/mipro/assets/images/loading.gif"
    },
    {
        "title": "Kasteel Cuvée du Chateau",
        "categories": "Belga, todo nuestro stock",
        "tipo": " Belgian Dark Strong Ale",
        "ABV": " 11%",
        "Formato": " Botella 33cl",
        "Origen": " Bélgica",
        "Descripción": " Sus creadores la denominan como  la joya de la corona, madurada por 10 años en",
        "img": "https://www.labuenacerveza.com/wp-content/themes/mipro/assets/images/loading.gif"
    },
    {
        "title": "Kasteel Donker",
        "categories": "Belga, Desde Belgium con Amor, todo nuestro stock",
        "tipo": " Belgian Dark Strong Ale",
        "ABV": " 11%",
        "Formato": " Botella 33cl",
        "Origen": " Bélgica",
        "Descripción": " Cerveza densa y cremosa de color marron con reflejos rojizos. El olor es a frutos secos",
        "img": "https://www.labuenacerveza.com/wp-content/themes/mipro/assets/images/loading.gif"
    },
    {
        "title": "La Calavera Resistir Es Vencer",
        "categories": "Acid Power, Sour, todo nuestro stock, Ultimas incorporaciones",
        "tipo": " Fruit Sour",
        "ABV": " 5%",
        "Formato": " Lata 33cl",
        "Origen": " Cataluña",
        "Descripción": " Cerveza ácida con albaricoque.",
        "img": "https://www.labuenacerveza.com/wp-content/themes/mipro/assets/images/loading.gif"
    },
    {
        "title": "La Chouffe Blonde",
        "categories": "Belga, Desde Belgium con Amor, todo nuestro stock",
        "tipo": " Belgian Golden Strong Ale",
        "ABV": " 8%",
        "Formato": " Botella 33cl",
        "Origen": " Bélgica",
        "Descripción": " Cerveza rubia belga. Aromas herbáceos y frutales. Gusto seco especiado y herbáceo. Regusto lupulado y un",
        "img": "https://www.labuenacerveza.com/wp-content/themes/mipro/assets/images/loading.gif"
    },
    {
        "title": "La Chouffe Blonde 75cl",
        "categories": "Belga, Desde Belgium con Amor, todo nuestro stock",
        "tipo": " Belgian Golden Strong Ale",
        "ABV": " 8%",
        "Formato": " Botella 75cl",
        "Origen": " Bélgica",
        "Descripción": " Cerveza rubia belga. Aromas herbáceos y frutales. Gusto seco especiado y herbáceo. Regusto lupulado y un",
        "img": "https://www.labuenacerveza.com/wp-content/themes/mipro/assets/images/loading.gif"
    },
    {
        "title": "La Grúa Amnesia Haze",
        "categories": "Hops Revolution, IPA, todo nuestro stock, Ultimas incorporaciones",
        "tipo": " New England Ipa",
        "ABV": " 6%",
        "Formato": " Lata 44cl",
        "Origen": " Cantabria",
        "Descripción": " New England IPA con lúpulos Citra, Mosaic y Cashmere.",
        "img": "https://www.labuenacerveza.com/wp-content/themes/mipro/assets/images/loading.gif"
    },
    {
        "title": "La Grúa Psychodelia Haze",
        "categories": "Hops Revolution, IPA, todo nuestro stock, Ultimas incorporaciones",
        "tipo": " New England Ipa",
        "ABV": " 6%",
        "Formato": " Lata 44cl",
        "Origen": " Cantabria",
        "Descripción": " New England IPA con lúpulos Mosaic, Citra y Motueka.",
        "img": "https://www.labuenacerveza.com/wp-content/themes/mipro/assets/images/loading.gif"
    },
    {
        "title": "La Quince / Guineu Black Barley Pedro Ximenez Oud Bruin",
        "categories": "Acid Power, Sour, todo nuestro stock, Ultimas incorporaciones",
        "tipo": " Oud Bruin",
        "ABV": " 14%",
        "Formato": " Botella 37,5cl",
        "Origen": " Madrid/Cataluña",
        "Descripción": " Inspirada en las Flemish Sour Bruin. Añejada 3 años en barrica de Pedro Ximenez.",
        "img": "https://www.labuenacerveza.com/wp-content/themes/mipro/assets/images/loading.gif"
    },
    {
        "title": "La Quince / Guineu Vanilla Black Velvet 2021",
        "categories": "Petroleos, Stout, todo nuestro stock, Ultimas incorporaciones",
        "tipo": " Russian Imperial Stout",
        "ABV": " 9,5%",
        "Formato": " Botella 33cl",
        "Origen": " Barcelona/ Madrid",
        "Descripción": " Colaboración entre Guineu y La Quince, elaborada en las instalaciones de la primera",
        "img": "https://www.labuenacerveza.com/wp-content/themes/mipro/assets/images/loading.gif"
    },
    {
        "title": "La Quince / Guineu Wild Sour II",
        "categories": "Acid Power, Lambic, Sour, todo nuestro stock, Ultimas incorporaciones",
        "tipo": " Wild / Sour",
        "ABV": " 5,7%",
        "Formato": " Botella 37,5cl",
        "Origen": " Madrid/Cataluña",
        "Descripción": " Wild Sour II es una Grape Ale de fermentación mixta con mosto",
        "img": "https://www.labuenacerveza.com/wp-content/themes/mipro/assets/images/loading.gif"
    },
    {
        "title": "La Quince / Subterfuge Stereoparty 2022",
        "categories": "Hops Revolution, IPA, todo nuestro stock, Ultimas incorporaciones",
        "tipo": " Session Hazy Ipa",
        "ABV": " 4,8%",
        "Formato": " Lata 44cl",
        "Origen": " Madrid",
        "Descripción": " Session Ipa colaboración con Subterfuge records con lúpulos Mosaic y Centennial.",
        "img": "https://www.labuenacerveza.com/wp-content/themes/mipro/assets/images/loading.gif"
    },
    {
        "title": "La Quince Beer House",
        "categories": "Belga, Klasikos Basikos, todo nuestro stock, Ultimas incorporaciones",
        "tipo": " Belgian Tripel",
        "ABV": " 7,3%",
        "Formato": " Lata 44cl",
        "Origen": " Madrid",
        "Descripción": " De su serie de cervezas Dragon Ball con levadura de un referente como Tripel",
        "img": "https://www.labuenacerveza.com/wp-content/themes/mipro/assets/images/loading.gif"
    },
    {
        "title": "La Quince Derby Winner",
        "categories": "Klasikos Basikos, Lager, todo nuestro stock, Ultimas incorporaciones",
        "tipo": " Lager / Helles",
        "ABV": " 5,2%",
        "Formato": " Lata 33cl",
        "Origen": " Madrid",
        "Descripción": " Helles rubia, ligera, suave y agradable, elaborada con lúpulo checo.",
        "img": "https://www.labuenacerveza.com/wp-content/themes/mipro/assets/images/loading.gif"
    },
    {
        "title": "La Quince Sinister Hops #2 Black IPA",
        "categories": "Hops Revolution, IPA, todo nuestro stock, Ultimas incorporaciones",
        "tipo": " Black Ipa",
        "ABV": " 6,8%",
        "Formato": " Lata 44cl",
        "Origen": " Madrid",
        "Descripción": " Black IPA muy lupulada y tropical de amargor medio. DDH El Dorado, Simcoe, Mosaic, Citra.",
        "img": "https://www.labuenacerveza.com/wp-content/themes/mipro/assets/images/loading.gif"
    },
    {
        "title": "La Quince Sinister Hops #3 Imperial Stout",
        "categories": "Petroleos, Stout, todo nuestro stock, Ultimas incorporaciones",
        "tipo": " Imperial Stout",
        "ABV": " 11%",
        "Formato": " Lata 44cl",
        "Origen": " Madrid",
        "Descripción": " Imperial Stout elaborada con el lúpulo Columbus de Queen Country Hop Farm y 7",
        "img": "https://www.labuenacerveza.com/wp-content/themes/mipro/assets/images/loading.gif"
    },
    {
        "title": "La Quince Sinister Sinister Hops #1 Doppelbock",
        "categories": "Klasikos Basikos, Lager, todo nuestro stock, Ultimas incorporaciones",
        "tipo": " Doppelbock",
        "ABV": " 7,2%",
        "Formato": " Lata 44cl",
        "Origen": " Madrid",
        "Descripción": " Doppelbock con el lúpulo Sapphir de Queen Country Hop.",
        "img": "https://www.labuenacerveza.com/wp-content/themes/mipro/assets/images/loading.gif"
    },
    {
        "title": "La Trappe Quadrupel",
        "categories": "Belga, Desde Belgium con Amor, todo nuestro stock",
        "tipo": " Belgian Quadrupel",
        "ABV": " 10%",
        "Formato": " Botella 33cl",
        "Origen": " Holanda",
        "Descripción": " Quadrupel es la cerveza más fuerte de La Trappe con un agradable color",
        "img": "https://www.labuenacerveza.com/wp-content/themes/mipro/assets/images/loading.gif"
    },
    {
        "title": "La Trappe Tripel",
        "categories": "Belga, Desde Belgium con Amor, todo nuestro stock",
        "tipo": " Belgian Tripel",
        "ABV": " 8%",
        "Formato": " Botella 33cl",
        "Origen": " Holanda",
        "Descripción": " Cerveza trapense, rubia dorada con una capa de espuma blanca. Aromas afrutados de",
        "img": "https://www.labuenacerveza.com/wp-content/themes/mipro/assets/images/loading.gif"
    },
    {
        "title": "Laugar Aupa Tovarisch",
        "categories": "Petroleos, Stout, todo nuestro stock",
        "tipo": " Russian Imperial Stout",
        "ABV": " 12%",
        "Formato": " Botella 33cl",
        "Origen": " País Vasco",
        "Descripción": " Cerveza de color negro y mucho cuerpo. Aroma tostados y torrefactos que se envuelve",
        "img": "https://www.labuenacerveza.com/wp-content/themes/mipro/assets/images/loading.gif"
    },
    {
        "title": "Lervig 3 Bean Stout",
        "categories": "Petroleos, Stout, todo nuestro stock, Ultimas incorporaciones",
        "tipo": " Imperial Stout",
        "ABV": " 12%",
        "Formato": " Lata 33cl",
        "Origen": " Holanda",
        "Descripción": " Stout elaborada con haba tonka, vainilla y cacao.",
        "img": "https://www.labuenacerveza.com/wp-content/themes/mipro/assets/images/loading.gif"
    },
    {
        "title": "Lervig Hoppy Joe",
        "categories": "Caramelazos, Red Ale, todo nuestro stock, Ultimas incorporaciones",
        "tipo": " Red Ale",
        "ABV": " 4,7%",
        "Formato": " Lata 33cl",
        "Origen": " Noruega",
        "Descripción": " Red ale con lúpulos Simcoe, Chinook y Nelson Sauvin. Y maltas caramelo y chocolate.",
        "img": "https://www.labuenacerveza.com/wp-content/themes/mipro/assets/images/loading.gif"
    },
    {
        "title": "Lervig Pilsner",
        "categories": "Klasikos Basikos, Lager, todo nuestro stock, Ultimas incorporaciones",
        "tipo": " Pilsner",
        "ABV": " 4,7%",
        "Formato": " Lata 50cl",
        "Origen": " Noruega",
        "Descripción": " Pilsner de color dorado claro, aromas a cereal y herbal con final amargo ligero.",
        "img": "https://www.labuenacerveza.com/wp-content/themes/mipro/assets/images/loading.gif"
    },
    {
        "title": "Les Trois Mousquetaires Imperial Stout",
        "categories": "Petroleos, Stout, todo nuestro stock",
        "tipo": " Imperial Stout",
        "ABV": " 11,5%",
        "Formato": " Botella 75cl",
        "Origen": " Canada",
        "Descripción": " Cerveza Imperial Stout, con café, añejada en barriles de bourbon, elaborada una vez al",
        "img": "https://www.labuenacerveza.com/wp-content/themes/mipro/assets/images/loading.gif"
    },
    {
        "title": "Les Trois Mousquetaires-Porter Baltique Gran Cuvée",
        "categories": "Petroleos, Porter, todo nuestro stock",
        "tipo": " Baltic Porter",
        "ABV": " 10%",
        "Formato": " Botella 75cl",
        "Origen": " Canada",
        "Descripción": " Cerveza envejecida durante meses en barricas de roble que anteriormente han contenido Bourbon y Brandy",
        "img": "https://www.labuenacerveza.com/wp-content/themes/mipro/assets/images/loading.gif"
    },
    {
        "title": "Les Trois Mousquetaires-Porter Baltique Gran Cuvée Edición BBF",
        "categories": "Petroleos, Porter, todo nuestro stock",
        "tipo": " Baltic Porter",
        "ABV": " 10%",
        "Formato": " Botella 75cl",
        "Origen": " Canada",
        "Descripción": " Edición Barcelona Beer Festival con café y lactosa. Cerveza envejecida durante meses en barricas",
        "img": "https://www.labuenacerveza.com/wp-content/themes/mipro/assets/images/loading.gif"
    },
    {
        "title": "Lindemans Framboise",
        "categories": "Belga, Desde Belgium con Amor, Into the wild, Lambic, todo nuestro stock",
        "tipo": " Fruit Lambic",
        "ABV": " 2,5%",
        "Formato": " Botella 25cl",
        "Origen": " Bélgica",
        "Descripción": " Cerveza Lambic afrutada con una adición de zumo de frambuesas, de fermentación espontánea y 2,5%",
        "img": "https://www.labuenacerveza.com/wp-content/themes/mipro/assets/images/loading.gif"
    },
    {
        "title": "Lindemans Kriek",
        "categories": "Belga, Desde Belgium con Amor, Into the wild, Lambic, todo nuestro stock",
        "tipo": " Fruit Lambic",
        "ABV": " 3,5%",
        "Formato": " Botella 25cl",
        "Origen": " Bélgica",
        "Descripción": " Cerveza Lambic afrutada con una adición de zumo de cerezas, de fermentación espontánea y 3,5% de alcohol.",
        "img": "https://www.labuenacerveza.com/wp-content/themes/mipro/assets/images/loading.gif"
    },
    {
        "title": "Lo Vilot Farm True Blood",
        "categories": "Acid Power, Berliner Weisse, Sour, todo nuestro stock, Ultimas incorporaciones",
        "tipo": " Imperial Fruit Sour",
        "ABV": " 8%",
        "Formato": " Lata 33cl",
        "Origen": " Cataluña",
        "Descripción": " Cerveza ácida elaborada con frambuesas y cacao.",
        "img": "https://www.labuenacerveza.com/wp-content/themes/mipro/assets/images/loading.gif"
    },
    {
        "title": "Magic Rock Fantasma",
        "categories": "Hops Revolution, IPA, Sin Gluten, todo nuestro stock, Ultimas incorporaciones",
        "tipo": " Ipa / Sin Gluten",
        "ABV": " 6,5%",
        "Formato": " Lata 33cl",
        "Origen": " Inglaterra",
        "Descripción": " Ipa sin gluten con lúpulos T 90 Citra y Magnum. Toques afrutados y",
        "img": "https://www.labuenacerveza.com/wp-content/themes/mipro/assets/images/loading.gif"
    },
    {
        "title": "Malandar Seis",
        "categories": "Hops Revolution, IPA, todo nuestro stock, Ultimas incorporaciones",
        "tipo": " Doble Ipa",
        "ABV": " 8%",
        "Formato": " Lata 44cl",
        "Origen": " Andalucía",
        "Descripción": " New England Dipa elaborada con lúpulos Talus y Cryo Sabro.",
        "img": "https://www.labuenacerveza.com/wp-content/themes/mipro/assets/images/loading.gif"
    },
    {
        "title": "Mikkeller Energibajer",
        "categories": "sin Alcohol, todo nuestro stock, Trigo",
        "tipo": " American Wheat Sin Alcohol 0,0",
        "ABV": " 0,0%",
        "Formato": " Botella 33cl",
        "Origen": " Dinamarca",
        "Descripción": " Cerveza de Trigo lupulada 0,0 alcohol. En nariz es una mezcla de melocotones",
        "img": "https://www.labuenacerveza.com/wp-content/themes/mipro/assets/images/loading.gif"
    },
    {
        "title": "Mitika Inguma",
        "categories": "Hops Revolution, IPA, todo nuestro stock, Ultimas incorporaciones",
        "tipo": " American Ipa",
        "ABV": " 6,5%",
        "Formato": " Botella 33cl",
        "Origen": " Navarra",
        "Descripción": " American Ipa.",
        "img": "https://www.labuenacerveza.com/wp-content/themes/mipro/assets/images/loading.gif"
    },
    {
        "title": "Naparbier Crazy Brown",
        "categories": "brown Ale, Caramelazos, todo nuestro stock, Ultimas incorporaciones",
        "tipo": " Imperial Brown Ale",
        "ABV": " 8,7%",
        "Formato": " Lata 44cl",
        "Origen": " Navarra",
        "Descripción": " Imperial Brown Ale con Lúpulos. H. Hersbucker y Tettnanger. Crazy Brown, una cerveza maltosa",
        "img": "https://www.labuenacerveza.com/wp-content/themes/mipro/assets/images/loading.gif"
    },
    {
        "title": "Naparbier Hop ´n´ Tasty",
        "categories": "Hops Revolution, IPA, todo nuestro stock, Ultimas incorporaciones",
        "tipo": " New England Ipa",
        "ABV": " 6,3%",
        "Formato": " Lata 44cl",
        "Origen": " Navarra",
        "Descripción": " Neipa con Lúpulos Mosaic, Amarillo, Citra, Simcoe.",
        "img": "https://www.labuenacerveza.com/wp-content/themes/mipro/assets/images/loading.gif"
    },
    {
        "title": "Naparbier Paranoid",
        "categories": "Hops Revolution, IPA, todo nuestro stock, Ultimas incorporaciones",
        "tipo": " West Coast Ipa",
        "ABV": " 6,2%",
        "Formato": " Lata 44cl",
        "Origen": " Navarra",
        "Descripción": " West Coast Ipa con  Lúpulos Simcoe y Citra.",
        "img": "https://www.labuenacerveza.com/wp-content/themes/mipro/assets/images/loading.gif"
    },
    {
        "title": "Naparbier Shine On",
        "categories": "Hops Revolution, IPA, todo nuestro stock, Ultimas incorporaciones",
        "tipo": " Doble New England Ipa",
        "ABV": " 8%",
        "Formato": " Lata 44cl",
        "Origen": " Navarra",
        "Descripción": " Doble Neipa con Lúpulos Mosaic, Simcoe y Loral Cryo.",
        "img": "https://www.labuenacerveza.com/wp-content/themes/mipro/assets/images/loading.gif"
    },
    {
        "title": "Naparbier Smile",
        "categories": "Hops Revolution, IPA, todo nuestro stock, Ultimas incorporaciones",
        "tipo": " New England Ipa",
        "ABV": " 6,4%",
        "Formato": " Lata 44cl",
        "Origen": " Navarra",
        "Descripción": " Neipa con Lúpulos Citra y Cryo Sabro.",
        "img": "https://www.labuenacerveza.com/wp-content/themes/mipro/assets/images/loading.gif"
    },
    {
        "title": "Nepomucen Jean-Michel²",
        "categories": "Petroleos, Stout, todo nuestro stock, Ultimas incorporaciones",
        "tipo": " Coffe Stout",
        "ABV": " 8,5%",
        "Formato": " Lata 50cl",
        "Origen": " Polonia",
        "Descripción": " Stout con café de Brasil, coco y vainilla.",
        "img": "https://www.labuenacerveza.com/wp-content/themes/mipro/assets/images/loading.gif"
    },
    {
        "title": "Orval",
        "categories": "Belga, Desde Belgium con Amor, todo nuestro stock",
        "tipo": " Belgian Pale Ale",
        "ABV": " 6,2%",
        "Formato": " Botella 33cl",
        "Origen": " Bélgica",
        "Descripción": " Cerveza con denominación de origen Trapense, 6,2%de alcohol, de alta fermentación y con segunda y tercera",
        "img": "https://www.labuenacerveza.com/wp-content/themes/mipro/assets/images/loading.gif"
    },
    {
        "title": "Oskar Blues Can-O-Bliss Resinous",
        "categories": "Hops Revolution, IPA, todo nuestro stock, Ultimas incorporaciones",
        "tipo": " New England Ipa",
        "ABV": " 7,2%",
        "Formato": " Lata 35cl",
        "Origen": " Estados Unidos",
        "Descripción": " Neipa con aromas cítricos y resinosos. Lúpulos HBC 692, Meridien, Saphir y Bravo.",
        "img": "https://www.labuenacerveza.com/wp-content/themes/mipro/assets/images/loading.gif"
    },
    {
        "title": "Oso Brew / North Brewing The Newest Normal",
        "categories": "Hops Revolution, IPA, todo nuestro stock, Ultimas incorporaciones",
        "tipo": " Hazy Doble Ipa",
        "ABV": " 8,2%",
        "Formato": " Lata 44cl",
        "Origen": " Madrid",
        "Descripción": " Doble Ipa colaboración con los Ingleses North Brewing, con lúpulos Cashmere, Cascade y Mosaic.",
        "img": "https://www.labuenacerveza.com/wp-content/themes/mipro/assets/images/loading.gif"
    },
    {
        "title": "Oud Beersel Framboise 37cl",
        "categories": "Acid Power, Belga, Desde Belgium con Amor, Into the wild, Lambic, todo nuestro stock",
        "tipo": " Fruit Lambic",
        "ABV": " 5%",
        "Formato": " Botella 37,5cl",
        "Origen": " Bélgica",
        "Descripción": " El uso de las auténticas frambuesas y el Lambic envejecido en barriles de madera, es el",
        "img": "https://www.labuenacerveza.com/wp-content/themes/mipro/assets/images/loading.gif"
    },
    {
        "title": "Oud Beersel Oude Geuze Vieille 2019 75cl",
        "categories": "Acid Power, Belga, Desde Belgium con Amor, Into the wild, Lambic, todo nuestro stock",
        "tipo": " Lambic Gueuze",
        "ABV": " 6%",
        "Formato": " Botella 75cl",
        "Origen": " Bélgica",
        "Descripción": " Lambic Geuze, blend entre las dos cervezas, una envejecida y una joven. Cerveza de fermentación espontánea",
        "img": "https://www.labuenacerveza.com/wp-content/themes/mipro/assets/images/loading.gif"
    },
    {
        "title": "Oud Beersel Oude Geuze Vieille 37cl",
        "categories": "Acid Power, Belga, Desde Belgium con Amor, Into the wild, Lambic, todo nuestro stock",
        "tipo": " Lambic Gueuze",
        "ABV": " 6%",
        "Formato": " Botella 37,5cl",
        "Origen": " Bélgica",
        "Descripción": " Lambic Geuze, blend entre las dos cervezas, una envejecida y una joven. Cerveza de fermentación espontánea",
        "img": "https://www.labuenacerveza.com/wp-content/themes/mipro/assets/images/loading.gif"
    },
    {
        "title": "Oud Beersel Oude Geuze Vieille Barrel Selection Foeder 21 37cl",
        "categories": "Acid Power, Belga, Desde Belgium con Amor, Into the wild, Lambic, todo nuestro stock",
        "tipo": " Lambic Gueuze",
        "ABV": " 6,5%",
        "Formato": " Botella 37,5cl",
        "Origen": " Bélgica",
        "Descripción": " Lambic madurada durante 4 años en barrica de vino. Esta Lambic se combina con otras Lambic",
        "img": "https://www.labuenacerveza.com/wp-content/themes/mipro/assets/images/loading.gif"
    },
    {
        "title": "Oud Beersel Oude Kriek Vieille 37cl",
        "categories": "Acid Power, Belga, Desde Belgium con Amor, Into the wild, Lambic, todo nuestro stock",
        "tipo": " Fruit Lambic",
        "ABV": " 6%",
        "Formato": " Botella 37,5cl",
        "Origen": " Bélgica",
        "Descripción": " Oud Beersel madurada en viejos barriles de madera y elaborada con cerezas naturales 400 gramos de",
        "img": "https://www.labuenacerveza.com/wp-content/themes/mipro/assets/images/loading.gif"
    },
    {
        "title": "Oud Beersel Oude Pijpen 2020 37cl",
        "categories": "Acid Power, Belga, Desde Belgium con Amor, Into the wild, Lambic, todo nuestro stock",
        "tipo": " Lambic Gueuze",
        "ABV": " 6,5%",
        "Formato": " Botella 37,5cl",
        "Origen": " Bélgica",
        "Descripción": " Gueuze maduradas en barricas antiguas de la cervecera con capacidad cada una para 650 litros, utilizadas",
        "img": "https://www.labuenacerveza.com/wp-content/themes/mipro/assets/images/loading.gif"
    },
    {
        "title": "Oude Beersel Green Walnut 75cl",
        "categories": "Acid Power, Belga, Desde Belgium con Amor, Into the wild, Lambic, todo nuestro stock",
        "tipo": " Fruit Lambic",
        "ABV": " 6%",
        "Formato": " Botella 75cl",
        "Origen": " Bélgica",
        "Descripción": " Una sorprendente e innovadora cerveza Lambic. En la producción, se utilizan frutos de nueces verdes añadidos a la",
        "img": "https://www.labuenacerveza.com/wp-content/themes/mipro/assets/images/loading.gif"
    },
    {
        "title": "Pulfer Black Blizzard",
        "categories": "Hops Revolution, IPA, todo nuestro stock, Ultimas incorporaciones",
        "tipo": " Doble Black Ipa",
        "ABV": " 8%",
        "Formato": " Lata 50cl",
        "Origen": " Croacia",
        "Descripción": " Doble Black Ipa con lúpulos Cashmere, Mosaic, Simcoe y Columbus.",
        "img": "https://www.labuenacerveza.com/wp-content/themes/mipro/assets/images/loading.gif"
    },
    {
        "title": "Pulfer Landsky",
        "categories": "Hops Revolution, IPA, todo nuestro stock, Ultimas incorporaciones",
        "tipo": " Session Ipa",
        "ABV": " 4,5%",
        "Formato": " Lata 50cl",
        "Origen": " Croacia",
        "Descripción": " Session Ipa",
        "img": "https://www.labuenacerveza.com/wp-content/themes/mipro/assets/images/loading.gif"
    },
    {
        "title": "Pulfer Perpetuum Mobile",
        "categories": "Hops Revolution, IPA, todo nuestro stock, Ultimas incorporaciones",
        "tipo": " West Coast Ipa",
        "ABV": " 6,4%",
        "Formato": " Lata 50cl",
        "Origen": " Croacia",
        "Descripción": " West Coast Ipa con lúpulos Amarillo, Citra y Chinook.",
        "img": "https://www.labuenacerveza.com/wp-content/themes/mipro/assets/images/loading.gif"
    },
    {
        "title": "Pulfer Tapu Pia",
        "categories": "Hops Revolution, IPA, todo nuestro stock, Ultimas incorporaciones",
        "tipo": " Doble Ipa",
        "ABV": " 8,2%",
        "Formato": " Lata 50cl",
        "Origen": " Croacia",
        "Descripción": " Doble Ipa con lúpulos Neozelandeses Nelson Sauvin, Motueka, Pacifica y Pacific Jade.",
        "img": "https://www.labuenacerveza.com/wp-content/themes/mipro/assets/images/loading.gif"
    },
    {
        "title": "Redneck Brea",
        "categories": "Petroleos, Stout, todo nuestro stock, Ultimas incorporaciones",
        "tipo": " Imperial Stout",
        "ABV": " 8,5%",
        "Formato": " Botella 33cl",
        "Origen": " Cantabria",
        "Descripción": "  Imperial stout color negro intenso con buena capa de fina espuma beige. Aromas y sabores",
        "img": "https://www.labuenacerveza.com/wp-content/themes/mipro/assets/images/loading.gif"
    },
    {
        "title": "Redneck General Lee",
        "categories": "Barley Wine, Caramelazos, todo nuestro stock, Ultimas incorporaciones",
        "tipo": " Barley Wine",
        "ABV": " 12%",
        "Formato": " Botella 33cl",
        "Origen": " Cantabria",
        "Descripción": " American Barley Wine con Maltas  Maris Otter, Munich, Melanoidin, Caramalt y Avena. Lupulo Cascade.",
        "img": "https://www.labuenacerveza.com/wp-content/themes/mipro/assets/images/loading.gif"
    },
    {
        "title": "Redneck Teniente Dan’up",
        "categories": "Petroleos, Stout, todo nuestro stock, Ultimas incorporaciones",
        "tipo": " Pastry Stout",
        "ABV": " 8,5%",
        "Formato": " Botella 33cl",
        "Origen": " Cantabria",
        "Descripción": " Cerveza Pastry Stout con Fresa, Cacao y Lactosa.",
        "img": "https://www.labuenacerveza.com/wp-content/themes/mipro/assets/images/loading.gif"
    },
    {
        "title": "Río Azul R/A 19 Tropical Breeze",
        "categories": "Acid Power, Sour, todo nuestro stock, Ultimas incorporaciones",
        "tipo": " Pastry Fruit Sour",
        "ABV": " 6,5%",
        "Formato": " Lata 44cl",
        "Origen": " Andalucía",
        "Descripción": " Ácida, refrescante, con mango verde y fruta de la pasión.",
        "img": "https://www.labuenacerveza.com/wp-content/themes/mipro/assets/images/loading.gif"
    },
    {
        "title": "Rio Azul R/A 23 JUICY PALE ALE",
        "categories": "Hops Revolution, Pale Ale, todo nuestro stock, Ultimas incorporaciones",
        "tipo": " New England Pale Ale",
        "ABV": " 4,2%",
        "Formato": " Lata 44cl",
        "Origen": " Andalucía",
        "Descripción": " Neapa refrescante y tropical, con notas a pino, otorgadas por el Citra",
        "img": "https://www.labuenacerveza.com/wp-content/themes/mipro/assets/images/loading.gif"
    },
    {
        "title": "Saison Dupont",
        "categories": "Belga, Desde Belgium con Amor, Saison, todo nuestro stock",
        "tipo": " Saison",
        "ABV": " 6,5%",
        "Formato": " 33cl",
        "Origen": " Bélgica",
        "Descripción": " De color anaranjado, refrescante pero con cuerpo. Color ámbar pálido y turbio, espuma abundante y consistente.",
        "img": "https://www.labuenacerveza.com/wp-content/themes/mipro/assets/images/loading.gif"
    },
    {
        "title": "Saltus Aupa Carnales",
        "categories": "Petroleos, Stout, todo nuestro stock, Ultimas incorporaciones",
        "tipo": " Imperial Stout",
        "ABV": " 11%",
        "Formato": " Botella 33cl",
        "Origen": " País Vasco",
        "Descripción": " Imperial Stout con chipotle, cacao del Amazonas, café de Panama, catui, almendra cruda, gengibre, melocotón en",
        "img": "https://www.labuenacerveza.com/wp-content/themes/mipro/assets/images/loading.gif"
    },
    {
        "title": "Saltus Labana Ta Sardexka",
        "categories": "Petroleos, Stout, todo nuestro stock, Ultimas incorporaciones",
        "tipo": " Imperial Stout",
        "ABV": " 10,6%",
        "Formato": " Botella 33cl",
        "Origen": " País Vasco",
        "Descripción": " Imperial Stout con canela y cacao.",
        "img": "https://www.labuenacerveza.com/wp-content/themes/mipro/assets/images/loading.gif"
    },
    {
        "title": "Saltus Zakarro",
        "categories": "Hops Revolution, IPA, todo nuestro stock, Ultimas incorporaciones",
        "tipo": " Doble Ipa",
        "ABV": " 8%",
        "Formato": " Lata 33cl",
        "Origen": " País Vasco",
        "Descripción": " Dipa de color cobrizo y apariencia turbia. En aroma y sabor resulta una explosión tropical",
        "img": "https://www.labuenacerveza.com/wp-content/themes/mipro/assets/images/loading.gif"
    },
    {
        "title": "Samuel Adams Boston Lager",
        "categories": "Klasikos Basikos, Lager, todo nuestro stock",
        "tipo": " Viena Lager",
        "ABV": " 4,6%",
        "Formato": " Botella 33cl",
        "Origen": " Estados Unidos",
        "Descripción": "Cerveza americana tipo Lager Viena, de 4,9% de alcohol, de baja fermentación.",
        "img": "https://www.labuenacerveza.com/wp-content/themes/mipro/assets/images/loading.gif"
    },
    {
        "title": "Samuel Smith Imperial Stout",
        "categories": "Petroleos, Stout, todo nuestro stock",
        "tipo": " Imperial Stout",
        "ABV": " 7%",
        "Formato": " Botella 35cl",
        "Origen": " Inglaterra",
        "Descripción": " Imperial Stout con aromas a maltas tostadas, café y chocolate.",
        "img": "https://www.labuenacerveza.com/wp-content/themes/mipro/assets/images/loading.gif"
    },
    {
        "title": "Samuel Smith Organic Chocolate Stout",
        "categories": "Petroleos, Stout, todo nuestro stock, Ultimas incorporaciones",
        "tipo": " Stout",
        "ABV": " 5%",
        "Formato": " Botella 35cl",
        "Origen": " Inglaterra",
        "Descripción": " Cerveza Stout elaborada con cacao orgánico. Cerveza algo dulce y cremosa con mucho aroma y sabor",
        "img": "https://www.labuenacerveza.com/wp-content/themes/mipro/assets/images/loading.gif"
    },
    {
        "title": "Samuel Smith Taddy Porter",
        "categories": "Petroleos, Porter, todo nuestro stock",
        "tipo": " Porter",
        "ABV": " 5%",
        "Formato": " Botella 35cl",
        "Origen": " Inglaterra",
        "Descripción": "Porter de color marrón oscuro, reflejos color rubí con espuma cremosa y consistente.El aroma a malta tostada",
        "img": "https://www.labuenacerveza.com/wp-content/themes/mipro/assets/images/loading.gif"
    },
    {
        "title": "Sanfrutos / Brussels Beer Project Attack",
        "categories": "Hops Revolution, IPA, todo nuestro stock, Ultimas incorporaciones",
        "tipo": " New England Doble Ipa",
        "ABV": " 8,5%",
        "Formato": " Lata 44cl",
        "Origen": " Segovia",
        "Descripción": " Una Doble IPA turbia con notas frutales, pináceas y tropicales",
        "img": "https://www.labuenacerveza.com/wp-content/themes/mipro/assets/images/loading.gif"
    },
    {
        "title": "Sanfrutos Barley Wine 2020",
        "categories": "Barley Wine, Caramelazos, todo nuestro stock, Ultimas incorporaciones",
        "tipo": " Barley Wine",
        "ABV": " 12,2%",
        "Formato": " Botella 33cl",
        "Origen": " Segovia",
        "Descripción": " De color oscuro con reflejos tostados, carbonatación baja, con una espuma oscura y fina. De cuerpo",
        "img": "https://www.labuenacerveza.com/wp-content/themes/mipro/assets/images/loading.gif"
    },
    {
        "title": "Schlenkerla Helles",
        "categories": "Klasikos Basikos, Lager, todo nuestro stock",
        "tipo": " Rauchbier Helles (ahumada)",
        "ABV": " 4,3%",
        "Formato": " Botella 50cl",
        "Origen": " Alemania",
        "Descripción": " Rauchbier (cerveza ahumada) de estilo Helles con 4.3%, ABV elaborada con finos",
        "img": "https://www.labuenacerveza.com/wp-content/themes/mipro/assets/images/loading.gif"
    },
    {
        "title": "Schlenkerla Rauchbier Marzen",
        "categories": "Klasikos Basikos, Lager, todo nuestro stock",
        "tipo": " Rauchbier Marzen (ahumada)",
        "ABV": " 5,1%",
        "Formato": " Botella50cl",
        "Origen": " Alemania",
        "Descripción": " Es una cerveza de tipo Marzen, pero cuya principal característica es que la base ahumada",
        "img": "https://www.labuenacerveza.com/wp-content/themes/mipro/assets/images/loading.gif"
    },
    {
        "title": "Schneider Weisse Helle Tap1",
        "categories": "Klasikos Basikos, todo nuestro stock, Trigo",
        "tipo": " Weizen, Weissbier (trigo alemán)",
        "ABV": " 4,9%",
        "Formato": " Botella 50cl",
        "Origen": " Alemania",
        "Descripción": " Está elaborada en un 60% con malta de trigo ",
        "img": "https://www.labuenacerveza.com/wp-content/themes/mipro/assets/images/loading.gif"
    },
    {
        "title": "Schneider Weisse Original Tap7",
        "categories": "Klasikos Basikos, todo nuestro stock, Trigo",
        "tipo": " Dunkelweizen (trigo alemán)",
        "ABV": " 5,4%",
        "Formato": " Botella 50cl",
        "Origen": " Alemania",
        "Descripción": " Toque de limón al principio seguido por notas de pan. Toque dulce",
        "img": "https://www.labuenacerveza.com/wp-content/themes/mipro/assets/images/loading.gif"
    },
    {
        "title": "Soma Beer 12 O’clock",
        "categories": "Hops Revolution, IPA, todo nuestro stock, Ultimas incorporaciones",
        "tipo": " New England Ipa",
        "ABV": " 6%",
        "Formato": " 33cl",
        "Origen": " Cataluña",
        "Descripción": " Neipa Ddh con lúpulos Enigma, HBC 630 y Galaxy.",
        "img": "https://www.labuenacerveza.com/wp-content/themes/mipro/assets/images/loading.gif"
    },
    {
        "title": "Soma Beer Double Idaho 7 Meets Azacca",
        "categories": "Hops Revolution, IPA, todo nuestro stock, Ultimas incorporaciones",
        "tipo": " Ddh Doble Ipa",
        "ABV": " 8%",
        "Formato": " 33cl",
        "Origen": " Cataluña",
        "Descripción": " Ddh Dipa con lúpulos Idaho 7, Idaho 7 Cryo, Azacca y Azacca Cryo.",
        "img": "https://www.labuenacerveza.com/wp-content/themes/mipro/assets/images/loading.gif"
    },
    {
        "title": "Soma Beer Honeypot",
        "categories": "Hops Revolution, IPA, todo nuestro stock, Ultimas incorporaciones",
        "tipo": " Ddh Ipa",
        "ABV": " 7,5%",
        "Formato": " 33cl",
        "Origen": " Cataluña",
        "Descripción": " Ipa Ddh con lúpulos Nelson, Mosaic Cryo, Azacca Cryo y HBC 630.",
        "img": "https://www.labuenacerveza.com/wp-content/themes/mipro/assets/images/loading.gif"
    },
    {
        "title": "Soma Beer Seed Phrase",
        "categories": "Hops Revolution, IPA, todo nuestro stock, Ultimas incorporaciones",
        "tipo": " Ddh Ipa",
        "ABV": " 6,5%",
        "Formato": " 33cl",
        "Origen": " Cataluña",
        "Descripción": " Ipa Ddh con lúpulos  Mosaic, Citra y Azacca Cryo.",
        "img": "https://www.labuenacerveza.com/wp-content/themes/mipro/assets/images/loading.gif"
    },
    {
        "title": "Sori Brewing Lost Room",
        "categories": "Petroleos, Porter, todo nuestro stock",
        "tipo": " Baltic Porter",
        "ABV": " 11,5%",
        "Formato": " Botella 33cl",
        "Origen": " Estonia",
        "Descripción": " Cerveza negra fuerte de estilo Imperial Baltic Porter de 11.5%, ABV elaborada con mucho caramelo",
        "img": "https://www.labuenacerveza.com/wp-content/themes/mipro/assets/images/loading.gif"
    },
    {
        "title": "St. Bernardus Abt 12",
        "categories": "Belga, Desde Belgium con Amor, todo nuestro stock",
        "tipo": " Quadrupel Belgian Dark Strong Ale",
        "ABV": " 10%",
        "Formato": " Botella 33cl",
        "Origen": " Bélgica",
        "Descripción": " Cerveza de color muy oscuro, con aromas marcados a levadura, caramelo, tostados",
        "img": "https://www.labuenacerveza.com/wp-content/themes/mipro/assets/images/loading.gif"
    },
    {
        "title": "St. Bernardus Prior 8",
        "categories": "Belga, Desde Belgium con Amor, todo nuestro stock",
        "tipo": " Belgian Dubbel",
        "ABV": " 8%",
        "Formato": " Botella 33cl",
        "Origen": " Bélgica",
        "Descripción": " Color pardo oscuro, muy turbio. La espuma es oscura. Olor a maltas oscuras y densas",
        "img": "https://www.labuenacerveza.com/wp-content/themes/mipro/assets/images/loading.gif"
    },
    {
        "title": "St. Bernardus Tripel",
        "categories": "Belga, Desde Belgium con Amor, todo nuestro stock",
        "tipo": " Belgian Tripel",
        "ABV": " 8%",
        "Formato": " Botella 33cl",
        "Origen": " Bélgica",
        "Descripción": " Rubia de color pálido ambarino, con aromas florales y afrutados y un sabor equilibrado y",
        "img": "https://www.labuenacerveza.com/wp-content/themes/mipro/assets/images/loading.gif"
    },
    {
        "title": "Stigbergets Juleljus",
        "categories": "Hops Revolution, IPA, todo nuestro stock, Ultimas incorporaciones",
        "tipo": " New England Ipa",
        "ABV": " 6,8%",
        "Formato": " Lata 44cl",
        "Origen": " Suecia",
        "Descripción": " Neipa",
        "img": "https://www.labuenacerveza.com/wp-content/themes/mipro/assets/images/loading.gif"
    },
    {
        "title": "Stigbergets Muddle",
        "categories": "Hops Revolution, IPA, todo nuestro stock, Ultimas incorporaciones",
        "tipo": " American Hazy Ipa",
        "ABV": " 7%",
        "Formato": " Lata 44cl",
        "Origen": " Suecia",
        "Descripción": " Hazy American Ipa con lúpulos Columbus, Simcoe y Citra.",
        "img": "https://www.labuenacerveza.com/wp-content/themes/mipro/assets/images/loading.gif"
    },
    {
        "title": "Stone Xocoveza",
        "categories": "Petroleos, Stout, todo nuestro stock",
        "tipo": " Imperial Stout",
        "ABV": " 8,1%",
        "Formato": " Lata 33cl",
        "Origen": " Estados Unidos/Alemania",
        "Descripción": " Imperial Stout con Lactosa, Café, Vainilla, Cacao, Pimientos picantes, Canela y Nuez moscada.",
        "img": "https://www.labuenacerveza.com/wp-content/themes/mipro/assets/images/loading.gif"
    },
    {
        "title": "Straffe Hendrik Quadrupel",
        "categories": "Belga, todo nuestro stock",
        "tipo": " Belgian Quadrupel",
        "ABV": " 11%",
        "Formato": " Botella 33cl",
        "Origen": " Bélgica",
        "Descripción": " Cerveza de color marrón oscuro, aroma alcohólico, dulce, toffe. Sabor a azúcar moreno, caramelo, maltoso y licoroso.",
        "img": "https://www.labuenacerveza.com/wp-content/themes/mipro/assets/images/loading.gif"
    },
    {
        "title": "Straffe Hendrik Tripel",
        "categories": "Belga, Desde Belgium con Amor, todo nuestro stock",
        "tipo": " Belgian Tripel",
        "ABV": " 9%",
        "Formato": " Botella 33cl",
        "Origen": " Bélgica",
        "Descripción": " Cerveza de color amarillo dorado, con aromas especiados, dulce, cítricos y afrutados. Sabor dulce, cereal, pan y especias",
        "img": "https://www.labuenacerveza.com/wp-content/themes/mipro/assets/images/loading.gif"
    },
    {
        "title": "Struise Pannepot Vintage 2020",
        "categories": "Belga, Caramelazos, Desde Belgium con Amor, todo nuestro stock",
        "tipo": " Belgian Dark Strong Ale",
        "ABV": " 10%",
        "Formato": " Botella 33cl",
        "Origen": " Bélgica",
        "Descripción": " Color marrón oscuro. Aromas a maltas caramelo, frutos secos, frutas pasas, café y final licoroso.",
        "img": "https://www.labuenacerveza.com/wp-content/themes/mipro/assets/images/loading.gif"
    },
    {
        "title": "Stu Mostów Nanaimo Bar Nitro Stout",
        "categories": "Petroleos, Stout, todo nuestro stock, Ultimas incorporaciones",
        "tipo": " Pastry Stout",
        "ABV": " 6,1%",
        "Formato": " Botella 33cl",
        "Origen": " Polonia",
        "Descripción": " Cerveza inspirada en el postre canadiense de chocolate Nanaimo. Con vainilla, coco, almendra y chocolate.",
        "img": "https://www.labuenacerveza.com/wp-content/themes/mipro/assets/images/loading.gif"
    },
    {
        "title": "Stu Mostów Salamander Milk Stout Chocolate Nitro",
        "categories": "Petroleos, Stout, todo nuestro stock, Ultimas incorporaciones",
        "tipo": " Milk Stout",
        "ABV": " 5,7%",
        "Formato": " Botella 50cl",
        "Origen": " Polonia",
        "Descripción": " Notas maltosas de chocolate, caramelo y café.",
        "img": "https://www.labuenacerveza.com/wp-content/themes/mipro/assets/images/loading.gif"
    },
    {
        "title": "Sudden Death Doom Boy",
        "categories": "Hops Revolution, IPA, todo nuestro stock, Ultimas incorporaciones",
        "tipo": " Hazy Doble Ipa",
        "ABV": " 8%",
        "Formato": " Lata 44cl",
        "Origen": " Alemania",
        "Descripción": " Hazy Dipa elaborada con lúpulos Mosaic BBC, Bru-1 y HBC 586.",
        "img": "https://www.labuenacerveza.com/wp-content/themes/mipro/assets/images/loading.gif"
    },
    {
        "title": "The Garden Imperial Raspberry, Coffee & Cacao Sour",
        "categories": "Acid Power, Berliner Weisse, Sour, todo nuestro stock, Ultimas incorporaciones",
        "tipo": " Imperia Fruit Sour",
        "ABV": " 7,5%",
        "Formato": " Lata 44cl",
        "Origen": " Croacia",
        "Descripción": " Imperial Sour con Frambuesa, café y cacao.",
        "img": "https://www.labuenacerveza.com/wp-content/themes/mipro/assets/images/loading.gif"
    },
    {
        "title": "Trappistes Rochefort 10",
        "categories": "Belga, Desde Belgium con Amor, todo nuestro stock",
        "tipo": " Belgian Dark Strong Ale",
        "ABV": " 11,3%",
        "Formato": " Botella 33cl",
        "Origen": " Belgica",
        "Descripción": " Cerveza Trapense de color oscuro, con aromas a pasas, a fruta",
        "img": "https://www.labuenacerveza.com/wp-content/themes/mipro/assets/images/loading.gif"
    },
    {
        "title": "Trappistes Rochefort 6",
        "categories": "Belga, Desde Belgium con Amor, todo nuestro stock",
        "tipo": " Belgian Strong Ale",
        "ABV": " 7,5%",
        "Formato": " Botella 33cl",
        "Origen": " Belgica",
        "Descripción": " Cerveza con denominación origen Trapense, 7,5% de alcohol, de alta fermentación",
        "img": "https://www.labuenacerveza.com/wp-content/themes/mipro/assets/images/loading.gif"
    },
    {
        "title": "Trappistes Rochefort 8",
        "categories": "Belga, Desde Belgium con Amor, todo nuestro stock",
        "tipo": " Belgian Dark Strong Ale",
        "ABV": " 9,2%",
        "Formato": " Botella 33cl",
        "Origen": " Belgica",
        "Descripción": " Cerveza Trapense color marrón rojizo, aroma complejo afrutado y herbáceo ",
        "img": "https://www.labuenacerveza.com/wp-content/themes/mipro/assets/images/loading.gif"
    },
    {
        "title": "Trappistes Rochefort Triple Extra",
        "categories": "Belga, Desde Belgium con Amor, todo nuestro stock",
        "tipo": " Belgian Tripel",
        "ABV": " 8,1%",
        "Formato": " Botella 33cl",
        "Origen": " Belgica",
        "Descripción": " Color amarillo corona de espuma blanca, aromas y sabores a cereal y frutas blancas",
        "img": "https://www.labuenacerveza.com/wp-content/themes/mipro/assets/images/loading.gif"
    },
    {
        "title": "Tripel Karmeliet",
        "categories": "Belga, Desde Belgium con Amor, todo nuestro stock",
        "tipo": " Belgian Tripel",
        "ABV": " 8,4%",
        "Formato": " Botella 33cl",
        "Origen": " Bélgica",
        "Descripción": " Cerveza de estilo Belgian Tripel . De color amarillo oro, contiene tres cereales": " cebada, avena y trigo.",
        "img": "https://www.labuenacerveza.com/wp-content/themes/mipro/assets/images/loading.gif"
    },
    {
        "title": "True Brew Greetings From…",
        "categories": "Hops Revolution, IPA, todo nuestro stock, Ultimas incorporaciones",
        "tipo": " New England Ipa",
        "ABV": " 6,7%",
        "Formato": " Lata 44cl",
        "Origen": " Alemania",
        "Descripción": " Neipa elaborada con doble dry hopping de lúpulos Citra, Mosaic y El Dorado.",
        "img": "https://www.labuenacerveza.com/wp-content/themes/mipro/assets/images/loading.gif"
    },
    {
        "title": "True Brew Somewhere Nowhere",
        "categories": "Hops Revolution, IPA, todo nuestro stock, Ultimas incorporaciones",
        "tipo": " New England Ipa",
        "ABV": " 6,5%",
        "Formato": " Lata 44cl",
        "Origen": " Alemania",
        "Descripción": " Neipa elaborada con doble dry hopping de lúpulos Talus, Citra y Amarillo.",
        "img": "https://www.labuenacerveza.com/wp-content/themes/mipro/assets/images/loading.gif"
    },
    {
        "title": "True Brew White Noise",
        "categories": "Hops Revolution, IPA, todo nuestro stock, Ultimas incorporaciones",
        "tipo": " Doble Ipa",
        "ABV": " 8%",
        "Formato": " Lata 44cl",
        "Origen": " Alemania",
        "Descripción": " Dipa elaborada con doble dry hopping de lúpulos Citra y Bru-1.",
        "img": "https://www.labuenacerveza.com/wp-content/themes/mipro/assets/images/loading.gif"
    },
    {
        "title": "Vault City Mango Session Sour",
        "categories": "Acid Power, Lambic, Sour, todo nuestro stock, Ultimas incorporaciones",
        "tipo": " Fruit Sour",
        "ABV": " 4,5%",
        "Formato": " Botella 33cl",
        "Origen": " Escocia",
        "Descripción": " Sour con Mango.",
        "img": "https://www.labuenacerveza.com/wp-content/themes/mipro/assets/images/loading.gif"
    },
    {
        "title": "Vault City Raspberry Sour",
        "categories": "Acid Power, Lambic, Sour, todo nuestro stock, Ultimas incorporaciones",
        "tipo": " Fruit Sour",
        "ABV": " 5%",
        "Formato": " Botella 33cl",
        "Origen": " Escocia",
        "Descripción": " Sour con frambuesas.",
        "img": "https://www.labuenacerveza.com/wp-content/themes/mipro/assets/images/loading.gif"
    },
    {
        "title": "Vault City Tropical Sour",
        "categories": "Acid Power, Lambic, Sour, todo nuestro stock, Ultimas incorporaciones",
        "tipo": " Fruit Sour",
        "ABV": " 5,2%",
        "Formato": " Botella 33cl",
        "Origen": " Escocia",
        "Descripción": " Sour con piña, maracuyá y guayaba.",
        "img": "https://www.labuenacerveza.com/wp-content/themes/mipro/assets/images/loading.gif"
    },
    {
        "title": "Weihenstephaner HefeWeissbier",
        "categories": "Klasikos Basikos, todo nuestro stock, Trigo",
        "tipo": " Weizen, Weissbier (trigo alemán)",
        "ABV": " 5,4%",
        "Formato": " Botella 50cl",
        "Origen": " Alemania",
        "Descripción": " Cerveza de trigo estilo Hefeweizen. De color amarillento, con espuma densa",
        "img": "https://www.labuenacerveza.com/wp-content/themes/mipro/assets/images/loading.gif"
    },
    {
        "title": "Weihenstephaner Vitus",
        "categories": "Klasikos Basikos, todo nuestro stock, Trigo",
        "tipo": " Weizenbock (trigo Alemán)",
        "ABV": " 7,7%",
        "Formato": " Botella 50cl",
        "Origen": " Alemania",
        "Descripción": " Una cerveza dorada de trigo con alto contenido alcohólico y aromática.",
        "img": "https://www.labuenacerveza.com/wp-content/themes/mipro/assets/images/loading.gif"
    },
    {
        "title": "Westmalle Dubbel",
        "categories": "Belga, Desde Belgium con Amor, todo nuestro stock",
        "tipo": " Belgian Dubbel",
        "ABV": " 7%",
        "Formato": " Botella 33cl",
        "Origen": " Belgica",
        "Descripción": " Cerveza con denominación de origen trapense, de 7% de alcohol, de alta fermentación",
        "img": "https://www.labuenacerveza.com/wp-content/themes/mipro/assets/images/loading.gif"
    },
    {
        "title": "Westmalle Tripel",
        "categories": "Belga, Desde Belgium con Amor, todo nuestro stock",
        "tipo": " Belgian Tripel",
        "ABV": " 9,5%",
        "Formato": " Botella 33cl",
        "Origen": " Belgica",
        "Descripción": " Cerveza Trapense, 9.5% de alcohol, de alta fermentación y con segunda fermentación en barrica",
        "img": "https://www.labuenacerveza.com/wp-content/themes/mipro/assets/images/loading.gif"
    },
    {
        "title": "Wychwood Hobgoblin Ruby",
        "categories": "brown Ale, Caramelazos, todo nuestro stock",
        "tipo": " English Brown Ale",
        "ABV": " 5,2%",
        "Formato": " Botella 50cl",
        "Origen": " Inglaterra",
        "Descripción": " Brown ale británica elaborada con maltas Pale, Crystal y malta Chocolate; y lúpulos",
        "img": "https://www.labuenacerveza.com/wp-content/themes/mipro/assets/images/loading.gif"
    },
    {
        "title": "Wylie Borrowed Nostalgia",
        "categories": "Hops Revolution, IPA, todo nuestro stock, Ultimas incorporaciones",
        "tipo": " Doble Ipa",
        "ABV": " 8%",
        "Formato": " Lata 44cl",
        "Origen": " Cataluña",
        "Descripción": " Dipa double dry-hopped con lúpulos Mosaic y Citra.",
        "img": "https://www.labuenacerveza.com/wp-content/themes/mipro/assets/images/loading.gif"
    },
    {
        "title": "Wylie Jabalipa",
        "categories": "Hops Revolution, IPA, todo nuestro stock, Ultimas incorporaciones",
        "tipo": " American Hazy Ipa",
        "ABV": " 5,7%",
        "Formato": " Lata 44cl",
        "Origen": " Cataluña",
        "Descripción": " Hazy Ipa.",
        "img": "https://www.labuenacerveza.com/wp-content/themes/mipro/assets/images/loading.gif"
    },
    {
        "title": "Wylie Revuelta De Funaná",
        "categories": "Hops Revolution, Pale Ale, todo nuestro stock, Ultimas incorporaciones",
        "tipo": " American Pale Ale",
        "ABV": " 5%",
        "Formato": " Lata 44cl",
        "Origen": " Cataluña",
        "Descripción": " Apa.",
        "img": "https://www.labuenacerveza.com/wp-content/themes/mipro/assets/images/loading.gif"
    },
    {
        "title": "Zeta Red Glow",
        "categories": "Hops Revolution, IPA, todo nuestro stock, Ultimas incorporaciones",
        "tipo": " NZ New Englan Ipa",
        "ABV": " 6,5%",
        "Formato": " Lata 44cl",
        "Origen": " Valencia",
        "Descripción": " Neipa con lúpulos Neozeladeses Wai-iti, Rakau, Cryo Mosaic y Galaxy.",
        "img": "https://www.labuenacerveza.com/wp-content/themes/mipro/assets/images/loading.gif"
    }
]